Compiled from "ShootSomeRocks.java"
public class ShootSomeRocks extends java.applet.Applet implements java.lang.Runnable{
java.lang.Thread game;

boolean initialized;

game2d.Bitmap backbuf;

java.awt.image.BufferedImage bi;

boolean go_ahead;

boolean restart_game;

boolean paused;

int game_mode;

float menu_stars_angle;

float menu_stars_scale;

int pause_timer;

int pulse;

int menu_delay;

int old_highscore;

boolean paintok;

int MAX_EXPS;

int MAX_HITS;

int MAX_POINTS;

int MAX_SHOTS;

int MAX_ROCKS;

int MAX_METEORS;

int MAX_UFOS;

int MAX_UFOSHOTS;

Ship ship;

Exp[] exp;

Hit[] hit;

Points[] point;

Rock[] rock;

Meteor[] meteor;

Shot[] shot;

Ufo[] ufo;

Ufoshot[] ufoshot;

Powerup powerup;

Extralife extralife;

game2d.FontBmp font16x32;

int rock_count;

int shot_timer;

int lives;

int nextExtralifeScore;

game2d.Bitmap tile;

game2d.Sound sound;

game2d.Input input;

int MAX_LIGHTS;

game2d.PropList plist;

game2d.Light[] light;

long gameTime;

long frameTime;

long fps_count;

long fps;

long newfps;

long oldfps;

long nextFrameStart;

java.lang.String scroller;

int scrolltick;

int scrollpos;

char[] scrolltemp;

public ShootSomeRocks();
  Code:
   0:	aload_0
   1:	invokespecial	#1; //Method java/applet/Applet."<init>":()V
   4:	aload_0
   5:	aconst_null
   6:	putfield	#2; //Field game:Ljava/lang/Thread;
   9:	aload_0
   10:	iconst_0
   11:	putfield	#3; //Field initialized:Z
   14:	aload_0
   15:	iconst_0
   16:	putfield	#4; //Field go_ahead:Z
   19:	aload_0
   20:	iconst_1
   21:	putfield	#5; //Field restart_game:Z
   24:	aload_0
   25:	iconst_0
   26:	putfield	#6; //Field paused:Z
   29:	aload_0
   30:	iconst_0
   31:	putfield	#7; //Field game_mode:I
   34:	aload_0
   35:	fconst_0
   36:	putfield	#8; //Field menu_stars_angle:F
   39:	aload_0
   40:	fconst_1
   41:	putfield	#9; //Field menu_stars_scale:F
   44:	aload_0
   45:	iconst_0
   46:	putfield	#10; //Field pause_timer:I
   49:	aload_0
   50:	iconst_0
   51:	putfield	#11; //Field menu_delay:I
   54:	aload_0
   55:	iconst_0
   56:	putfield	#12; //Field old_highscore:I
   59:	aload_0
   60:	iconst_0
   61:	putfield	#13; //Field paintok:Z
   64:	aload_0
   65:	bipush	32
   67:	putfield	#14; //Field MAX_EXPS:I
   70:	aload_0
   71:	bipush	32
   73:	putfield	#15; //Field MAX_HITS:I
   76:	aload_0
   77:	bipush	32
   79:	putfield	#16; //Field MAX_POINTS:I
   82:	aload_0
   83:	bipush	32
   85:	putfield	#17; //Field MAX_SHOTS:I
   88:	aload_0
   89:	bipush	32
   91:	putfield	#18; //Field MAX_ROCKS:I
   94:	aload_0
   95:	bipush	32
   97:	putfield	#19; //Field MAX_METEORS:I
   100:	aload_0
   101:	bipush	32
   103:	putfield	#20; //Field MAX_UFOS:I
   106:	aload_0
   107:	bipush	32
   109:	putfield	#21; //Field MAX_UFOSHOTS:I
   112:	aload_0
   113:	new	#22; //class Ship
   116:	dup
   117:	invokespecial	#23; //Method Ship."<init>":()V
   120:	putfield	#24; //Field ship:LShip;
   123:	aload_0
   124:	aload_0
   125:	getfield	#14; //Field MAX_EXPS:I
   128:	anewarray	#25; //class Exp
   131:	putfield	#26; //Field exp:[LExp;
   134:	aload_0
   135:	aload_0
   136:	getfield	#15; //Field MAX_HITS:I
   139:	anewarray	#27; //class Hit
   142:	putfield	#28; //Field hit:[LHit;
   145:	aload_0
   146:	aload_0
   147:	getfield	#16; //Field MAX_POINTS:I
   150:	anewarray	#29; //class Points
   153:	putfield	#30; //Field point:[LPoints;
   156:	aload_0
   157:	aload_0
   158:	getfield	#18; //Field MAX_ROCKS:I
   161:	anewarray	#31; //class Rock
   164:	putfield	#32; //Field rock:[LRock;
   167:	aload_0
   168:	aload_0
   169:	getfield	#19; //Field MAX_METEORS:I
   172:	anewarray	#33; //class Meteor
   175:	putfield	#34; //Field meteor:[LMeteor;
   178:	aload_0
   179:	aload_0
   180:	getfield	#17; //Field MAX_SHOTS:I
   183:	anewarray	#35; //class Shot
   186:	putfield	#36; //Field shot:[LShot;
   189:	aload_0
   190:	aload_0
   191:	getfield	#20; //Field MAX_UFOS:I
   194:	anewarray	#37; //class Ufo
   197:	putfield	#38; //Field ufo:[LUfo;
   200:	aload_0
   201:	aload_0
   202:	getfield	#21; //Field MAX_UFOSHOTS:I
   205:	anewarray	#39; //class Ufoshot
   208:	putfield	#40; //Field ufoshot:[LUfoshot;
   211:	aload_0
   212:	new	#41; //class Powerup
   215:	dup
   216:	invokespecial	#42; //Method Powerup."<init>":()V
   219:	putfield	#43; //Field powerup:LPowerup;
   222:	aload_0
   223:	new	#44; //class Extralife
   226:	dup
   227:	invokespecial	#45; //Method Extralife."<init>":()V
   230:	putfield	#46; //Field extralife:LExtralife;
   233:	aload_0
   234:	new	#47; //class game2d/FontBmp
   237:	dup
   238:	getstatic	#48; //Field Sprite.font16x32:Lgame2d/Anim;
   241:	invokevirtual	#49; //Method game2d/Anim.frame:()Lgame2d/Bitmap;
   244:	bipush	16
   246:	invokespecial	#50; //Method game2d/FontBmp."<init>":(Lgame2d/Bitmap;I)V
   249:	putfield	#51; //Field font16x32:Lgame2d/FontBmp;
   252:	aload_0
   253:	new	#52; //class game2d/Bitmap
   256:	dup
   257:	sipush	256
   260:	sipush	256
   263:	invokespecial	#53; //Method game2d/Bitmap."<init>":(II)V
   266:	putfield	#54; //Field tile:Lgame2d/Bitmap;
   269:	aload_0
   270:	bipush	8
   272:	putfield	#55; //Field MAX_LIGHTS:I
   275:	aload_0
   276:	new	#56; //class game2d/PropList
   279:	dup
   280:	aload_0
   281:	getfield	#55; //Field MAX_LIGHTS:I
   284:	invokespecial	#57; //Method game2d/PropList."<init>":(I)V
   287:	putfield	#58; //Field plist:Lgame2d/PropList;
   290:	aload_0
   291:	aload_0
   292:	getfield	#55; //Field MAX_LIGHTS:I
   295:	anewarray	#59; //class game2d/Light
   298:	putfield	#60; //Field light:[Lgame2d/Light;
   301:	aload_0
   302:	ldc2_w	#61; //long 8000000l
   305:	putfield	#63; //Field gameTime:J
   308:	aload_0
   309:	ldc2_w	#64; //long 16666666l
   312:	putfield	#66; //Field frameTime:J
   315:	aload_0
   316:	lconst_0
   317:	putfield	#67; //Field fps_count:J
   320:	aload_0
   321:	lconst_0
   322:	putfield	#68; //Field fps:J
   325:	aload_0
   326:	lconst_0
   327:	putfield	#69; //Field newfps:J
   330:	aload_0
   331:	lconst_0
   332:	putfield	#70; //Field oldfps:J
   335:	aload_0
   336:	new	#71; //class java/lang/String
   339:	dup
   340:	ldc	#72; //String                                              This game is easy, just shoot at stuff and collect weaponry. Extra life if you rescue the broken-down ship! Controls: Click mouse to move, Space to fire.
   342:	invokespecial	#73; //Method java/lang/String."<init>":(Ljava/lang/String;)V
   345:	putfield	#74; //Field scroller:Ljava/lang/String;
   348:	aload_0
   349:	iconst_0
   350:	putfield	#75; //Field scrolltick:I
   353:	aload_0
   354:	iconst_0
   355:	putfield	#76; //Field scrollpos:I
   358:	aload_0
   359:	bipush	41
   361:	newarray char
   363:	putfield	#77; //Field scrolltemp:[C
   366:	return

public void init();
  Code:
   0:	aload_0
   1:	iconst_0
   2:	putfield	#7; //Field game_mode:I
   5:	aload_0
   6:	iconst_0
   7:	putfield	#4; //Field go_ahead:Z
   10:	aload_0
   11:	getfield	#3; //Field initialized:Z
   14:	ifeq	18
   17:	return
   18:	invokestatic	#78; //Method game2d/Trig.init:()V
   21:	sipush	12345
   24:	invokestatic	#79; //Method game2d/Rnd.set:(I)V
   27:	iconst_0
   28:	invokestatic	#80; //Method game2d/Blend.setMode:(I)V
   31:	aload_0
   32:	new	#52; //class game2d/Bitmap
   35:	dup
   36:	getstatic	#81; //Field game2d/Screen.w:I
   39:	getstatic	#82; //Field game2d/Screen.h:I
   42:	invokespecial	#53; //Method game2d/Bitmap."<init>":(II)V
   45:	putfield	#83; //Field backbuf:Lgame2d/Bitmap;
   48:	aload_0
   49:	lconst_0
   50:	putfield	#68; //Field fps:J
   53:	new	#84; //class java/awt/image/DataBufferInt
   56:	dup
   57:	aload_0
   58:	getfield	#83; //Field backbuf:Lgame2d/Bitmap;
   61:	getfield	#85; //Field game2d/Bitmap.data:[I
   64:	aload_0
   65:	getfield	#83; //Field backbuf:Lgame2d/Bitmap;
   68:	getfield	#86; //Field game2d/Bitmap.w:I
   71:	aload_0
   72:	getfield	#83; //Field backbuf:Lgame2d/Bitmap;
   75:	getfield	#87; //Field game2d/Bitmap.h:I
   78:	imul
   79:	invokespecial	#88; //Method java/awt/image/DataBufferInt."<init>":([II)V
   82:	astore_2
   83:	iconst_4
   84:	newarray int
   86:	dup
   87:	iconst_0
   88:	ldc	#89; //int 16711680
   90:	iastore
   91:	dup
   92:	iconst_1
   93:	ldc	#90; //int 65280
   95:	iastore
   96:	dup
   97:	iconst_2
   98:	sipush	255
   101:	iastore
   102:	dup
   103:	iconst_3
   104:	ldc	#91; //int -16777216
   106:	iastore
   107:	astore_3
   108:	aload_2
   109:	aload_0
   110:	getfield	#83; //Field backbuf:Lgame2d/Bitmap;
   113:	getfield	#86; //Field game2d/Bitmap.w:I
   116:	aload_0
   117:	getfield	#83; //Field backbuf:Lgame2d/Bitmap;
   120:	getfield	#87; //Field game2d/Bitmap.h:I
   123:	aload_0
   124:	getfield	#83; //Field backbuf:Lgame2d/Bitmap;
   127:	getfield	#86; //Field game2d/Bitmap.w:I
   130:	aload_3
   131:	aconst_null
   132:	invokestatic	#92; //Method java/awt/image/Raster.createPackedRaster:(Ljava/awt/image/DataBuffer;III[ILjava/awt/Point;)Ljava/awt/image/WritableRaster;
   135:	astore	4
   137:	invokestatic	#93; //Method java/awt/image/ColorModel.getRGBdefault:()Ljava/awt/image/ColorModel;
   140:	astore	5
   142:	aload_0
   143:	new	#94; //class java/awt/image/BufferedImage
   146:	dup
   147:	aload	5
   149:	aload	4
   151:	iconst_0
   152:	aconst_null
   153:	invokespecial	#95; //Method java/awt/image/BufferedImage."<init>":(Ljava/awt/image/ColorModel;Ljava/awt/image/WritableRaster;ZLjava/util/Hashtable;)V
   156:	putfield	#96; //Field bi:Ljava/awt/image/BufferedImage;
   159:	aload_0
   160:	getstatic	#97; //Field java/awt/Color.BLACK:Ljava/awt/Color;
   163:	invokevirtual	#98; //Method setBackground:(Ljava/awt/Color;)V
   166:	aload_0
   167:	invokevirtual	#99; //Method getSize:()Ljava/awt/Dimension;
   170:	astore	6
   172:	aload	6
   174:	getfield	#100; //Field java/awt/Dimension.width:I
   177:	putstatic	#101; //Field game2d/Screen.maxw:I
   180:	aload	6
   182:	getfield	#102; //Field java/awt/Dimension.height:I
   185:	putstatic	#103; //Field game2d/Screen.maxh:I
   188:	getstatic	#101; //Field game2d/Screen.maxw:I
   191:	getstatic	#81; //Field game2d/Screen.w:I
   194:	idiv
   195:	istore	7
   197:	iload	7
   199:	iconst_1
   200:	if_icmpge	206
   203:	iconst_1
   204:	istore	7
   206:	getstatic	#103; //Field game2d/Screen.maxh:I
   209:	getstatic	#82; //Field game2d/Screen.h:I
   212:	idiv
   213:	istore	8
   215:	iload	8
   217:	iconst_1
   218:	if_icmpge	224
   221:	iconst_1
   222:	istore	8
   224:	iload	7
   226:	iload	8
   228:	invokestatic	#104; //Method game2d/Int.min:(II)I
   231:	putstatic	#105; //Field game2d/Screen.scale:I
   234:	getstatic	#81; //Field game2d/Screen.w:I
   237:	getstatic	#105; //Field game2d/Screen.scale:I
   240:	imul
   241:	putstatic	#106; //Field game2d/Screen.scaledw:I
   244:	getstatic	#82; //Field game2d/Screen.h:I
   247:	getstatic	#105; //Field game2d/Screen.scale:I
   250:	imul
   251:	putstatic	#107; //Field game2d/Screen.scaledh:I
   254:	getstatic	#101; //Field game2d/Screen.maxw:I
   257:	getstatic	#106; //Field game2d/Screen.scaledw:I
   260:	isub
   261:	iconst_2
   262:	idiv
   263:	putstatic	#108; //Field game2d/Screen.xpos:I
   266:	getstatic	#103; //Field game2d/Screen.maxh:I
   269:	getstatic	#107; //Field game2d/Screen.scaledh:I
   272:	isub
   273:	iconst_2
   274:	idiv
   275:	putstatic	#109; //Field game2d/Screen.ypos:I
   278:	iconst_0
   279:	istore_1
   280:	iload_1
   281:	aload_0
   282:	getfield	#14; //Field MAX_EXPS:I
   285:	if_icmpge	307
   288:	aload_0
   289:	getfield	#26; //Field exp:[LExp;
   292:	iload_1
   293:	new	#25; //class Exp
   296:	dup
   297:	invokespecial	#110; //Method Exp."<init>":()V
   300:	aastore
   301:	iinc	1, 1
   304:	goto	280
   307:	iconst_0
   308:	istore_1
   309:	iload_1
   310:	aload_0
   311:	getfield	#15; //Field MAX_HITS:I
   314:	if_icmpge	336
   317:	aload_0
   318:	getfield	#28; //Field hit:[LHit;
   321:	iload_1
   322:	new	#27; //class Hit
   325:	dup
   326:	invokespecial	#111; //Method Hit."<init>":()V
   329:	aastore
   330:	iinc	1, 1
   333:	goto	309
   336:	iconst_0
   337:	istore_1
   338:	iload_1
   339:	aload_0
   340:	getfield	#16; //Field MAX_POINTS:I
   343:	if_icmpge	365
   346:	aload_0
   347:	getfield	#30; //Field point:[LPoints;
   350:	iload_1
   351:	new	#29; //class Points
   354:	dup
   355:	invokespecial	#112; //Method Points."<init>":()V
   358:	aastore
   359:	iinc	1, 1
   362:	goto	338
   365:	iconst_0
   366:	istore_1
   367:	iload_1
   368:	aload_0
   369:	getfield	#18; //Field MAX_ROCKS:I
   372:	if_icmpge	394
   375:	aload_0
   376:	getfield	#32; //Field rock:[LRock;
   379:	iload_1
   380:	new	#31; //class Rock
   383:	dup
   384:	invokespecial	#113; //Method Rock."<init>":()V
   387:	aastore
   388:	iinc	1, 1
   391:	goto	367
   394:	iconst_0
   395:	istore_1
   396:	iload_1
   397:	aload_0
   398:	getfield	#19; //Field MAX_METEORS:I
   401:	if_icmpge	423
   404:	aload_0
   405:	getfield	#34; //Field meteor:[LMeteor;
   408:	iload_1
   409:	new	#33; //class Meteor
   412:	dup
   413:	invokespecial	#114; //Method Meteor."<init>":()V
   416:	aastore
   417:	iinc	1, 1
   420:	goto	396
   423:	iconst_0
   424:	istore_1
   425:	iload_1
   426:	aload_0
   427:	getfield	#17; //Field MAX_SHOTS:I
   430:	if_icmpge	452
   433:	aload_0
   434:	getfield	#36; //Field shot:[LShot;
   437:	iload_1
   438:	new	#35; //class Shot
   441:	dup
   442:	invokespecial	#115; //Method Shot."<init>":()V
   445:	aastore
   446:	iinc	1, 1
   449:	goto	425
   452:	iconst_0
   453:	istore_1
   454:	iload_1
   455:	aload_0
   456:	getfield	#20; //Field MAX_UFOS:I
   459:	if_icmpge	481
   462:	aload_0
   463:	getfield	#38; //Field ufo:[LUfo;
   466:	iload_1
   467:	new	#37; //class Ufo
   470:	dup
   471:	invokespecial	#116; //Method Ufo."<init>":()V
   474:	aastore
   475:	iinc	1, 1
   478:	goto	454
   481:	iconst_0
   482:	istore_1
   483:	iload_1
   484:	aload_0
   485:	getfield	#21; //Field MAX_UFOSHOTS:I
   488:	if_icmpge	510
   491:	aload_0
   492:	getfield	#40; //Field ufoshot:[LUfoshot;
   495:	iload_1
   496:	new	#39; //class Ufoshot
   499:	dup
   500:	invokespecial	#117; //Method Ufoshot."<init>":()V
   503:	aastore
   504:	iinc	1, 1
   507:	goto	483
   510:	iconst_0
   511:	istore_1
   512:	iload_1
   513:	aload_0
   514:	getfield	#55; //Field MAX_LIGHTS:I
   517:	if_icmpge	539
   520:	aload_0
   521:	getfield	#60; //Field light:[Lgame2d/Light;
   524:	iload_1
   525:	new	#59; //class game2d/Light
   528:	dup
   529:	invokespecial	#118; //Method game2d/Light."<init>":()V
   532:	aastore
   533:	iinc	1, 1
   536:	goto	512
   539:	aload_0
   540:	getfield	#55; //Field MAX_LIGHTS:I
   543:	invokestatic	#119; //Method game2d/Bitmap.init:(I)V
   546:	aload_0
   547:	new	#120; //class game2d/Input
   550:	dup
   551:	invokespecial	#121; //Method game2d/Input."<init>":()V
   554:	putfield	#122; //Field input:Lgame2d/Input;
   557:	aload_0
   558:	aload_0
   559:	getfield	#122; //Field input:Lgame2d/Input;
   562:	invokevirtual	#123; //Method addKeyListener:(Ljava/awt/event/KeyListener;)V
   565:	aload_0
   566:	aload_0
   567:	getfield	#122; //Field input:Lgame2d/Input;
   570:	invokevirtual	#124; //Method addMouseListener:(Ljava/awt/event/MouseListener;)V
   573:	aload_0
   574:	aload_0
   575:	getfield	#122; //Field input:Lgame2d/Input;
   578:	invokevirtual	#125; //Method addMouseMotionListener:(Ljava/awt/event/MouseMotionListener;)V
   581:	aload_0
   582:	new	#126; //class game2d/Sound
   585:	dup
   586:	invokespecial	#127; //Method game2d/Sound."<init>":()V
   589:	putfield	#128; //Field sound:Lgame2d/Sound;
   592:	aload_0
   593:	invokestatic	#129; //Method java/lang/System.nanoTime:()J
   596:	putfield	#130; //Field nextFrameStart:J
   599:	aload_0
   600:	new	#131; //class java/lang/Thread
   603:	dup
   604:	aload_0
   605:	invokespecial	#132; //Method java/lang/Thread."<init>":(Ljava/lang/Runnable;)V
   608:	putfield	#2; //Field game:Ljava/lang/Thread;
   611:	aload_0
   612:	getfield	#2; //Field game:Ljava/lang/Thread;
   615:	invokevirtual	#133; //Method java/lang/Thread.start:()V
   618:	aload_0
   619:	iconst_1
   620:	putfield	#3; //Field initialized:Z
   623:	return

public void start();
  Code:
   0:	return

public void run();
  Code:
   0:	invokestatic	#129; //Method java/lang/System.nanoTime:()J
   3:	lstore_1
   4:	aload_0
   5:	dup
   6:	getfield	#134; //Field pulse:I
   9:	iconst_4
   10:	iadd
   11:	putfield	#134; //Field pulse:I
   14:	aload_0
   15:	dup
   16:	getfield	#134; //Field pulse:I
   19:	sipush	1023
   22:	iand
   23:	putfield	#134; //Field pulse:I
   26:	aload_0
   27:	dup
   28:	getfield	#8; //Field menu_stars_angle:F
   31:	ldc	#135; //float 0.1f
   33:	fadd
   34:	putfield	#8; //Field menu_stars_angle:F
   37:	aload_0
   38:	getfield	#8; //Field menu_stars_angle:F
   41:	ldc	#136; //float 1023.0f
   43:	fcmpl
   44:	ifle	58
   47:	aload_0
   48:	dup
   49:	getfield	#8; //Field menu_stars_angle:F
   52:	ldc	#137; //float 1024.0f
   54:	fsub
   55:	putfield	#8; //Field menu_stars_angle:F
   58:	aload_0
   59:	getfield	#7; //Field game_mode:I
   62:	tableswitch{ //0 to 3
		0: 92;
		1: 124;
		2: 145;
		3: 166;
		default: 188 }
   92:	aload_0
   93:	invokevirtual	#138; //Method menuLoop:()Z
   96:	iconst_1
   97:	if_icmpne	188
   100:	aload_0
   101:	iconst_1
   102:	putfield	#7; //Field game_mode:I
   105:	aload_0
   106:	iconst_0
   107:	putfield	#4; //Field go_ahead:Z
   110:	aload_0
   111:	getstatic	#139; //Field Score.high:I
   114:	putfield	#12; //Field old_highscore:I
   117:	aload_0
   118:	invokespecial	#140; //Method restartGame:()V
   121:	goto	188
   124:	aload_0
   125:	invokevirtual	#141; //Method levelLoop:()Z
   128:	iconst_1
   129:	if_icmpne	188
   132:	aload_0
   133:	iconst_2
   134:	putfield	#7; //Field game_mode:I
   137:	aload_0
   138:	iconst_0
   139:	putfield	#4; //Field go_ahead:Z
   142:	goto	188
   145:	aload_0
   146:	invokevirtual	#142; //Method gameLoop:()Z
   149:	iconst_1
   150:	if_icmpne	188
   153:	aload_0
   154:	iconst_3
   155:	putfield	#7; //Field game_mode:I
   158:	aload_0
   159:	iconst_0
   160:	putfield	#4; //Field go_ahead:Z
   163:	goto	188
   166:	aload_0
   167:	invokevirtual	#143; //Method gameOverLoop:()Z
   170:	iconst_1
   171:	if_icmpne	188
   174:	aload_0
   175:	iconst_0
   176:	putfield	#7; //Field game_mode:I
   179:	aload_0
   180:	invokevirtual	#144; //Method resetScroll:()V
   183:	aload_0
   184:	iconst_0
   185:	putfield	#4; //Field go_ahead:Z
   188:	aload_0
   189:	dup
   190:	getfield	#130; //Field nextFrameStart:J
   193:	aload_0
   194:	getfield	#63; //Field gameTime:J
   197:	ladd
   198:	putfield	#130; //Field nextFrameStart:J
   201:	aload_0
   202:	getfield	#130; //Field nextFrameStart:J
   205:	invokestatic	#129; //Method java/lang/System.nanoTime:()J
   208:	lcmp
   209:	iflt	4
   212:	aload_0
   213:	getfield	#130; //Field nextFrameStart:J
   216:	invokestatic	#129; //Method java/lang/System.nanoTime:()J
   219:	lsub
   220:	lstore_3
   221:	lload_3
   222:	ldc2_w	#145; //long 1000000l
   225:	ldiv
   226:	lstore	5
   228:	lload_3
   229:	ldc2_w	#145; //long 1000000l
   232:	lrem
   233:	l2i
   234:	istore	7
   236:	lload_3
   237:	lconst_0
   238:	lcmp
   239:	ifle	254
   242:	lload	5
   244:	iload	7
   246:	invokestatic	#147; //Method java/lang/Thread.sleep:(JI)V
   249:	goto	254
   252:	astore	8
   254:	invokestatic	#129; //Method java/lang/System.nanoTime:()J
   257:	lstore	8
   259:	aload_0
   260:	dup
   261:	getfield	#67; //Field fps_count:J
   264:	lload	8
   266:	lload_1
   267:	lsub
   268:	ladd
   269:	putfield	#67; //Field fps_count:J
   272:	aload_0
   273:	getfield	#67; //Field fps_count:J
   276:	ldc2_w	#149; //long 1000000000l
   279:	lcmp
   280:	iflt	321
   283:	aload_0
   284:	lconst_0
   285:	putfield	#67; //Field fps_count:J
   288:	aload_0
   289:	aload_0
   290:	getfield	#70; //Field oldfps:J
   293:	aload_0
   294:	getfield	#68; //Field fps:J
   297:	ladd
   298:	ldc2_w	#151; //long 2l
   301:	ldiv
   302:	putfield	#69; //Field newfps:J
   305:	aload_0
   306:	aload_0
   307:	getfield	#68; //Field fps:J
   310:	putfield	#70; //Field oldfps:J
   313:	aload_0
   314:	lconst_0
   315:	putfield	#68; //Field fps:J
   318:	goto	331
   321:	aload_0
   322:	dup
   323:	getfield	#68; //Field fps:J
   326:	lconst_1
   327:	ladd
   328:	putfield	#68; //Field fps:J
   331:	aload_0
   332:	getfield	#13; //Field paintok:Z
   335:	ifne	406
   338:	aload_0
   339:	getfield	#7; //Field game_mode:I
   342:	tableswitch{ //0 to 3
		0: 372;
		1: 379;
		2: 386;
		3: 393;
		default: 397 }
   372:	aload_0
   373:	invokevirtual	#153; //Method menuFrame:()V
   376:	goto	397
   379:	aload_0
   380:	invokevirtual	#154; //Method levelFrame:()V
   383:	goto	397
   386:	aload_0
   387:	invokevirtual	#155; //Method gameFrame:()V
   390:	goto	397
   393:	aload_0
   394:	invokevirtual	#156; //Method gameOverFrame:()V
   397:	aload_0
   398:	iconst_1
   399:	putfield	#13; //Field paintok:Z
   402:	aload_0
   403:	invokevirtual	#157; //Method repaint:()V
   406:	goto	0
  Exception table:
   from   to  target type
   242   249   252   Class java/lang/InterruptedException


public boolean gameLoop();
  Code:
   0:	invokestatic	#158; //Method Stars.update:()V
   3:	aload_0
   4:	getfield	#122; //Field input:Lgame2d/Input;
   7:	bipush	81
   9:	invokevirtual	#159; //Method game2d/Input.getKey:(I)Z
   12:	ifeq	36
   15:	aload_0
   16:	getfield	#12; //Field old_highscore:I
   19:	putstatic	#139; //Field Score.high:I
   22:	aload_0
   23:	getfield	#128; //Field sound:Lgame2d/Sound;
   26:	invokevirtual	#160; //Method game2d/Sound.quiet:()V
   29:	aload_0
   30:	iconst_0
   31:	putfield	#7; //Field game_mode:I
   34:	iconst_1
   35:	ireturn
   36:	aload_0
   37:	getfield	#122; //Field input:Lgame2d/Input;
   40:	bipush	80
   42:	invokevirtual	#159; //Method game2d/Input.getKey:(I)Z
   45:	ifeq	82
   48:	aload_0
   49:	getfield	#10; //Field pause_timer:I
   52:	bipush	20
   54:	if_icmple	82
   57:	aload_0
   58:	iconst_0
   59:	putfield	#10; //Field pause_timer:I
   62:	aload_0
   63:	getfield	#6; //Field paused:Z
   66:	ifeq	77
   69:	aload_0
   70:	iconst_0
   71:	putfield	#6; //Field paused:Z
   74:	goto	82
   77:	aload_0
   78:	iconst_1
   79:	putfield	#6; //Field paused:Z
   82:	aload_0
   83:	dup
   84:	getfield	#10; //Field pause_timer:I
   87:	iconst_1
   88:	iadd
   89:	putfield	#10; //Field pause_timer:I
   92:	aload_0
   93:	getfield	#6; //Field paused:Z
   96:	ifeq	101
   99:	iconst_0
   100:	ireturn
   101:	invokestatic	#161; //Method game2d/Rnd.get:()I
   104:	bipush	31
   106:	iand
   107:	bipush	31
   109:	if_icmpne	162
   112:	iconst_0
   113:	istore_1
   114:	iload_1
   115:	getstatic	#162; //Field Level.ufos:I
   118:	if_icmpge	142
   121:	aload_0
   122:	getfield	#38; //Field ufo:[LUfo;
   125:	iload_1
   126:	aaload
   127:	getfield	#163; //Field Ufo.status:Z
   130:	ifne	136
   133:	goto	142
   136:	iinc	1, 1
   139:	goto	114
   142:	iload_1
   143:	getstatic	#162; //Field Level.ufos:I
   146:	if_icmpge	162
   149:	aload_0
   150:	getfield	#38; //Field ufo:[LUfo;
   153:	iload_1
   154:	aaload
   155:	aload_0
   156:	getfield	#24; //Field ship:LShip;
   159:	invokevirtual	#164; //Method Ufo.add:(LShip;)V
   162:	iconst_0
   163:	istore_1
   164:	iload_1
   165:	getstatic	#162; //Field Level.ufos:I
   168:	if_icmpge	206
   171:	aload_0
   172:	getfield	#38; //Field ufo:[LUfo;
   175:	iload_1
   176:	aaload
   177:	getfield	#163; //Field Ufo.status:Z
   180:	ifeq	200
   183:	aload_0
   184:	getfield	#128; //Field sound:Lgame2d/Sound;
   187:	aload_0
   188:	getfield	#38; //Field ufo:[LUfo;
   191:	iload_1
   192:	aaload
   193:	getfield	#165; //Field Ufo.sound:Lgame2d/Sample;
   196:	iconst_0
   197:	invokevirtual	#166; //Method game2d/Sound.play:(Lgame2d/Sample;Z)V
   200:	iinc	1, 1
   203:	goto	164
   206:	getstatic	#162; //Field Level.ufos:I
   209:	ifle	305
   212:	getstatic	#167; //Field Level.ufoshots:I
   215:	ifle	305
   218:	invokestatic	#161; //Method game2d/Rnd.get:()I
   221:	bipush	63
   223:	iand
   224:	bipush	63
   226:	if_icmpne	305
   229:	invokestatic	#161; //Method game2d/Rnd.get:()I
   232:	getstatic	#162; //Field Level.ufos:I
   235:	irem
   236:	istore_2
   237:	aload_0
   238:	getfield	#38; //Field ufo:[LUfo;
   241:	iload_2
   242:	aaload
   243:	getfield	#163; //Field Ufo.status:Z
   246:	ifeq	305
   249:	iconst_0
   250:	istore_1
   251:	iload_1
   252:	getstatic	#167; //Field Level.ufoshots:I
   255:	if_icmpge	279
   258:	aload_0
   259:	getfield	#40; //Field ufoshot:[LUfoshot;
   262:	iload_1
   263:	aaload
   264:	getfield	#168; //Field Ufoshot.status:Z
   267:	ifne	273
   270:	goto	279
   273:	iinc	1, 1
   276:	goto	251
   279:	iload_1
   280:	getstatic	#167; //Field Level.ufoshots:I
   283:	if_icmpge	305
   286:	aload_0
   287:	getfield	#40; //Field ufoshot:[LUfoshot;
   290:	iload_1
   291:	aaload
   292:	aload_0
   293:	getfield	#24; //Field ship:LShip;
   296:	aload_0
   297:	getfield	#38; //Field ufo:[LUfo;
   300:	iload_2
   301:	aaload
   302:	invokevirtual	#169; //Method Ufoshot.add:(LShip;LUfo;)V
   305:	aload_0
   306:	getfield	#24; //Field ship:LShip;
   309:	aload_0
   310:	getfield	#24; //Field ship:LShip;
   313:	getfield	#170; //Field Ship.y:F
   316:	aload_0
   317:	getfield	#122; //Field input:Lgame2d/Input;
   320:	getfield	#171; //Field game2d/Input.mousey:I
   323:	i2f
   324:	fsub
   325:	aload_0
   326:	getfield	#24; //Field ship:LShip;
   329:	getfield	#172; //Field Ship.x:F
   332:	aload_0
   333:	getfield	#122; //Field input:Lgame2d/Input;
   336:	getfield	#173; //Field game2d/Input.mousex:I
   339:	i2f
   340:	fsub
   341:	invokestatic	#174; //Method game2d/Trig.angle:(FF)F
   344:	putfield	#175; //Field Ship.angle:F
   347:	aload_0
   348:	getfield	#122; //Field input:Lgame2d/Input;
   351:	getfield	#176; //Field game2d/Input.button1:Z
   354:	ifeq	391
   357:	aload_0
   358:	getfield	#24; //Field ship:LShip;
   361:	getstatic	#177; //Field Powers.thrust:Z
   364:	invokevirtual	#178; //Method Ship.forward:(Z)V
   367:	getstatic	#177; //Field Powers.thrust:Z
   370:	ifeq	384
   373:	aload_0
   374:	getfield	#128; //Field sound:Lgame2d/Sound;
   377:	getstatic	#179; //Field Snd.thrust:Lgame2d/Sample;
   380:	iconst_0
   381:	invokevirtual	#166; //Method game2d/Sound.play:(Lgame2d/Sample;Z)V
   384:	iconst_1
   385:	putstatic	#180; //Field Powers.thrustActive:Z
   388:	goto	395
   391:	iconst_0
   392:	putstatic	#180; //Field Powers.thrustActive:Z
   395:	aload_0
   396:	getfield	#122; //Field input:Lgame2d/Input;
   399:	bipush	32
   401:	invokevirtual	#159; //Method game2d/Input.getKey:(I)Z
   404:	ifeq	426
   407:	aload_0
   408:	getfield	#181; //Field shot_timer:I
   411:	getstatic	#182; //Field Powers.shot_speed:I
   414:	if_icmple	426
   417:	aload_0
   418:	iconst_0
   419:	putfield	#181; //Field shot_timer:I
   422:	aload_0
   423:	invokespecial	#183; //Method addShot:()V
   426:	aload_0
   427:	getfield	#24; //Field ship:LShip;
   430:	invokevirtual	#184; //Method Ship.update:()V
   433:	aload_0
   434:	aload_0
   435:	getfield	#24; //Field ship:LShip;
   438:	aload_0
   439:	getfield	#32; //Field rock:[LRock;
   442:	getstatic	#185; //Field Level.rocks:I
   445:	invokespecial	#186; //Method findNearest:(Lgame2d/Prop;[Lgame2d/Prop;I)I
   448:	istore_3
   449:	iload_3
   450:	iconst_m1
   451:	if_icmpeq	502
   454:	aload_0
   455:	getfield	#24; //Field ship:LShip;
   458:	aload_0
   459:	getfield	#32; //Field rock:[LRock;
   462:	iload_3
   463:	aaload
   464:	invokestatic	#187; //Method game2d/Collision.check:(Lgame2d/Prop;Lgame2d/Prop;)Z
   467:	ifeq	502
   470:	aload_0
   471:	aload_0
   472:	getfield	#32; //Field rock:[LRock;
   475:	iload_3
   476:	aaload
   477:	invokevirtual	#188; //Method loseLife:(Lgame2d/Prop;)V
   480:	aload_0
   481:	dup
   482:	getfield	#189; //Field rock_count:I
   485:	iconst_1
   486:	isub
   487:	putfield	#189; //Field rock_count:I
   490:	aload_0
   491:	getfield	#189; //Field rock_count:I
   494:	iconst_1
   495:	if_icmpge	502
   498:	aload_0
   499:	invokespecial	#190; //Method levelUp:()V
   502:	aload_0
   503:	aload_0
   504:	getfield	#24; //Field ship:LShip;
   507:	aload_0
   508:	getfield	#34; //Field meteor:[LMeteor;
   511:	getstatic	#191; //Field Level.meteors:I
   514:	invokespecial	#186; //Method findNearest:(Lgame2d/Prop;[Lgame2d/Prop;I)I
   517:	istore_3
   518:	iload_3
   519:	iconst_m1
   520:	if_icmpeq	549
   523:	aload_0
   524:	getfield	#24; //Field ship:LShip;
   527:	aload_0
   528:	getfield	#34; //Field meteor:[LMeteor;
   531:	iload_3
   532:	aaload
   533:	invokestatic	#187; //Method game2d/Collision.check:(Lgame2d/Prop;Lgame2d/Prop;)Z
   536:	ifeq	549
   539:	aload_0
   540:	aload_0
   541:	getfield	#34; //Field meteor:[LMeteor;
   544:	iload_3
   545:	aaload
   546:	invokevirtual	#188; //Method loseLife:(Lgame2d/Prop;)V
   549:	aload_0
   550:	aload_0
   551:	getfield	#24; //Field ship:LShip;
   554:	aload_0
   555:	getfield	#38; //Field ufo:[LUfo;
   558:	getstatic	#162; //Field Level.ufos:I
   561:	invokespecial	#186; //Method findNearest:(Lgame2d/Prop;[Lgame2d/Prop;I)I
   564:	istore_3
   565:	iload_3
   566:	iconst_m1
   567:	if_icmpeq	596
   570:	aload_0
   571:	getfield	#24; //Field ship:LShip;
   574:	aload_0
   575:	getfield	#38; //Field ufo:[LUfo;
   578:	iload_3
   579:	aaload
   580:	invokestatic	#187; //Method game2d/Collision.check:(Lgame2d/Prop;Lgame2d/Prop;)Z
   583:	ifeq	596
   586:	aload_0
   587:	aload_0
   588:	getfield	#38; //Field ufo:[LUfo;
   591:	iload_3
   592:	aaload
   593:	invokevirtual	#188; //Method loseLife:(Lgame2d/Prop;)V
   596:	aload_0
   597:	aload_0
   598:	getfield	#24; //Field ship:LShip;
   601:	aload_0
   602:	getfield	#40; //Field ufoshot:[LUfoshot;
   605:	getstatic	#167; //Field Level.ufoshots:I
   608:	invokespecial	#186; //Method findNearest:(Lgame2d/Prop;[Lgame2d/Prop;I)I
   611:	istore_3
   612:	iload_3
   613:	iconst_m1
   614:	if_icmpeq	643
   617:	aload_0
   618:	getfield	#24; //Field ship:LShip;
   621:	aload_0
   622:	getfield	#40; //Field ufoshot:[LUfoshot;
   625:	iload_3
   626:	aaload
   627:	invokestatic	#187; //Method game2d/Collision.check:(Lgame2d/Prop;Lgame2d/Prop;)Z
   630:	ifeq	643
   633:	aload_0
   634:	aload_0
   635:	getfield	#40; //Field ufoshot:[LUfoshot;
   638:	iload_3
   639:	aaload
   640:	invokevirtual	#188; //Method loseLife:(Lgame2d/Prop;)V
   643:	iconst_0
   644:	istore_1
   645:	iload_1
   646:	getstatic	#192; //Field Level.shots:I
   649:	if_icmpge	1700
   652:	aload_0
   653:	getfield	#36; //Field shot:[LShot;
   656:	iload_1
   657:	aaload
   658:	invokevirtual	#193; //Method Shot.update:()V
   661:	aload_0
   662:	getfield	#36; //Field shot:[LShot;
   665:	iload_1
   666:	aaload
   667:	getfield	#194; //Field Shot.status:Z
   670:	ifeq	1694
   673:	aload_0
   674:	aload_0
   675:	getfield	#36; //Field shot:[LShot;
   678:	iload_1
   679:	aaload
   680:	aload_0
   681:	getfield	#32; //Field rock:[LRock;
   684:	getstatic	#185; //Field Level.rocks:I
   687:	invokespecial	#186; //Method findNearest:(Lgame2d/Prop;[Lgame2d/Prop;I)I
   690:	istore_3
   691:	iload_3
   692:	iconst_m1
   693:	if_icmpeq	1028
   696:	aload_0
   697:	getfield	#36; //Field shot:[LShot;
   700:	iload_1
   701:	aaload
   702:	aload_0
   703:	getfield	#32; //Field rock:[LRock;
   706:	iload_3
   707:	aaload
   708:	invokestatic	#187; //Method game2d/Collision.check:(Lgame2d/Prop;Lgame2d/Prop;)Z
   711:	ifeq	1028
   714:	aload_0
   715:	getfield	#36; //Field shot:[LShot;
   718:	iload_1
   719:	aaload
   720:	invokevirtual	#195; //Method Shot.remove:()V
   723:	aload_0
   724:	aload_0
   725:	getfield	#32; //Field rock:[LRock;
   728:	iload_3
   729:	aaload
   730:	getfield	#196; //Field Rock.x:F
   733:	aload_0
   734:	getfield	#32; //Field rock:[LRock;
   737:	iload_3
   738:	aaload
   739:	getfield	#197; //Field Rock.y:F
   742:	aload_0
   743:	getfield	#32; //Field rock:[LRock;
   746:	iload_3
   747:	aaload
   748:	getfield	#198; //Field Rock.speed:F
   751:	aload_0
   752:	getfield	#32; //Field rock:[LRock;
   755:	iload_3
   756:	aaload
   757:	getfield	#199; //Field Rock.dir:F
   760:	aload_0
   761:	getfield	#32; //Field rock:[LRock;
   764:	iload_3
   765:	aaload
   766:	getfield	#200; //Field Rock.angle:F
   769:	invokevirtual	#201; //Method addExplosion:(FFFFF)V
   772:	aload_0
   773:	getfield	#32; //Field rock:[LRock;
   776:	iload_3
   777:	aaload
   778:	getfield	#202; //Field Rock.points:I
   781:	invokestatic	#203; //Method Score.add:(I)V
   784:	aload_0
   785:	aload_0
   786:	getfield	#32; //Field rock:[LRock;
   789:	iload_3
   790:	aaload
   791:	getfield	#196; //Field Rock.x:F
   794:	aload_0
   795:	getfield	#32; //Field rock:[LRock;
   798:	iload_3
   799:	aaload
   800:	getfield	#197; //Field Rock.y:F
   803:	aload_0
   804:	getfield	#32; //Field rock:[LRock;
   807:	iload_3
   808:	aaload
   809:	getfield	#202; //Field Rock.points:I
   812:	invokevirtual	#204; //Method addPoint:(FFI)V
   815:	aload_0
   816:	getfield	#32; //Field rock:[LRock;
   819:	iload_3
   820:	aaload
   821:	getfield	#205; //Field Rock.type:I
   824:	tableswitch{ //0 to 2
		0: 852;
		1: 878;
		2: 904;
		default: 927 }
   852:	aload_0
   853:	getfield	#128; //Field sound:Lgame2d/Sound;
   856:	getstatic	#206; //Field Snd.rockexp3:Lgame2d/Sample;
   859:	iconst_1
   860:	invokevirtual	#166; //Method game2d/Sound.play:(Lgame2d/Sample;Z)V
   863:	aload_0
   864:	getfield	#32; //Field rock:[LRock;
   867:	iload_3
   868:	aaload
   869:	getstatic	#207; //Field Sprite.rock3:Lgame2d/Anim;
   872:	putfield	#208; //Field Rock.anim:Lgame2d/Anim;
   875:	goto	927
   878:	aload_0
   879:	getfield	#128; //Field sound:Lgame2d/Sound;
   882:	getstatic	#209; //Field Snd.rockexp2:Lgame2d/Sample;
   885:	iconst_1
   886:	invokevirtual	#166; //Method game2d/Sound.play:(Lgame2d/Sample;Z)V
   889:	aload_0
   890:	getfield	#32; //Field rock:[LRock;
   893:	iload_3
   894:	aaload
   895:	getstatic	#207; //Field Sprite.rock3:Lgame2d/Anim;
   898:	putfield	#208; //Field Rock.anim:Lgame2d/Anim;
   901:	goto	927
   904:	aload_0
   905:	getfield	#128; //Field sound:Lgame2d/Sound;
   908:	getstatic	#210; //Field Snd.rockexp1:Lgame2d/Sample;
   911:	iconst_1
   912:	invokevirtual	#166; //Method game2d/Sound.play:(Lgame2d/Sample;Z)V
   915:	aload_0
   916:	getfield	#32; //Field rock:[LRock;
   919:	iload_3
   920:	aaload
   921:	getstatic	#211; //Field Sprite.rock2:Lgame2d/Anim;
   924:	putfield	#208; //Field Rock.anim:Lgame2d/Anim;
   927:	aload_0
   928:	getfield	#32; //Field rock:[LRock;
   931:	iload_3
   932:	aaload
   933:	dup
   934:	getfield	#205; //Field Rock.type:I
   937:	iconst_1
   938:	isub
   939:	putfield	#205; //Field Rock.type:I
   942:	aload_0
   943:	getfield	#32; //Field rock:[LRock;
   946:	iload_3
   947:	aaload
   948:	invokestatic	#161; //Method game2d/Rnd.get:()I
   951:	bipush	8
   953:	irem
   954:	sipush	128
   957:	imul
   958:	bipush	64
   960:	iadd
   961:	sipush	1023
   964:	iand
   965:	i2f
   966:	putfield	#199; //Field Rock.dir:F
   969:	aload_0
   970:	getfield	#32; //Field rock:[LRock;
   973:	iload_3
   974:	aaload
   975:	dup
   976:	getfield	#198; //Field Rock.speed:F
   979:	ldc	#212; //float 1.25f
   981:	fmul
   982:	putfield	#198; //Field Rock.speed:F
   985:	aload_0
   986:	getfield	#32; //Field rock:[LRock;
   989:	iload_3
   990:	aaload
   991:	getfield	#205; //Field Rock.type:I
   994:	ifge	1028
   997:	aload_0
   998:	getfield	#32; //Field rock:[LRock;
   1001:	iload_3
   1002:	aaload
   1003:	invokevirtual	#213; //Method Rock.remove:()V
   1006:	aload_0
   1007:	dup
   1008:	getfield	#189; //Field rock_count:I
   1011:	iconst_1
   1012:	isub
   1013:	putfield	#189; //Field rock_count:I
   1016:	aload_0
   1017:	getfield	#189; //Field rock_count:I
   1020:	iconst_1
   1021:	if_icmpge	1028
   1024:	aload_0
   1025:	invokespecial	#190; //Method levelUp:()V
   1028:	aload_0
   1029:	aload_0
   1030:	getfield	#36; //Field shot:[LShot;
   1033:	iload_1
   1034:	aaload
   1035:	aload_0
   1036:	getfield	#34; //Field meteor:[LMeteor;
   1039:	getstatic	#191; //Field Level.meteors:I
   1042:	invokespecial	#186; //Method findNearest:(Lgame2d/Prop;[Lgame2d/Prop;I)I
   1045:	istore_3
   1046:	iload_3
   1047:	iconst_m1
   1048:	if_icmpeq	1190
   1051:	aload_0
   1052:	getfield	#36; //Field shot:[LShot;
   1055:	iload_1
   1056:	aaload
   1057:	aload_0
   1058:	getfield	#34; //Field meteor:[LMeteor;
   1061:	iload_3
   1062:	aaload
   1063:	invokestatic	#187; //Method game2d/Collision.check:(Lgame2d/Prop;Lgame2d/Prop;)Z
   1066:	ifeq	1190
   1069:	aload_0
   1070:	getfield	#128; //Field sound:Lgame2d/Sound;
   1073:	getstatic	#209; //Field Snd.rockexp2:Lgame2d/Sample;
   1076:	iconst_1
   1077:	invokevirtual	#166; //Method game2d/Sound.play:(Lgame2d/Sample;Z)V
   1080:	aload_0
   1081:	getfield	#36; //Field shot:[LShot;
   1084:	iload_1
   1085:	aaload
   1086:	invokevirtual	#195; //Method Shot.remove:()V
   1089:	aload_0
   1090:	aload_0
   1091:	getfield	#34; //Field meteor:[LMeteor;
   1094:	iload_3
   1095:	aaload
   1096:	getfield	#214; //Field Meteor.x:F
   1099:	aload_0
   1100:	getfield	#34; //Field meteor:[LMeteor;
   1103:	iload_3
   1104:	aaload
   1105:	getfield	#215; //Field Meteor.y:F
   1108:	aload_0
   1109:	getfield	#34; //Field meteor:[LMeteor;
   1112:	iload_3
   1113:	aaload
   1114:	getfield	#216; //Field Meteor.speed:F
   1117:	aload_0
   1118:	getfield	#34; //Field meteor:[LMeteor;
   1121:	iload_3
   1122:	aaload
   1123:	getfield	#217; //Field Meteor.dir:F
   1126:	aload_0
   1127:	getfield	#34; //Field meteor:[LMeteor;
   1130:	iload_3
   1131:	aaload
   1132:	getfield	#218; //Field Meteor.angle:F
   1135:	invokevirtual	#201; //Method addExplosion:(FFFFF)V
   1138:	aload_0
   1139:	getfield	#34; //Field meteor:[LMeteor;
   1142:	iload_3
   1143:	aaload
   1144:	getfield	#219; //Field Meteor.points:I
   1147:	invokestatic	#203; //Method Score.add:(I)V
   1150:	aload_0
   1151:	aload_0
   1152:	getfield	#34; //Field meteor:[LMeteor;
   1155:	iload_3
   1156:	aaload
   1157:	getfield	#214; //Field Meteor.x:F
   1160:	aload_0
   1161:	getfield	#34; //Field meteor:[LMeteor;
   1164:	iload_3
   1165:	aaload
   1166:	getfield	#215; //Field Meteor.y:F
   1169:	aload_0
   1170:	getfield	#34; //Field meteor:[LMeteor;
   1173:	iload_3
   1174:	aaload
   1175:	getfield	#219; //Field Meteor.points:I
   1178:	invokevirtual	#204; //Method addPoint:(FFI)V
   1181:	aload_0
   1182:	getfield	#34; //Field meteor:[LMeteor;
   1185:	iload_3
   1186:	aaload
   1187:	invokevirtual	#220; //Method Meteor.remove:()V
   1190:	aload_0
   1191:	aload_0
   1192:	getfield	#36; //Field shot:[LShot;
   1195:	iload_1
   1196:	aaload
   1197:	aload_0
   1198:	getfield	#38; //Field ufo:[LUfo;
   1201:	getstatic	#162; //Field Level.ufos:I
   1204:	invokespecial	#186; //Method findNearest:(Lgame2d/Prop;[Lgame2d/Prop;I)I
   1207:	istore_3
   1208:	iload_3
   1209:	iconst_m1
   1210:	if_icmpeq	1521
   1213:	aload_0
   1214:	getfield	#36; //Field shot:[LShot;
   1217:	iload_1
   1218:	aaload
   1219:	aload_0
   1220:	getfield	#38; //Field ufo:[LUfo;
   1223:	iload_3
   1224:	aaload
   1225:	invokestatic	#187; //Method game2d/Collision.check:(Lgame2d/Prop;Lgame2d/Prop;)Z
   1228:	ifeq	1521
   1231:	aload_0
   1232:	getfield	#36; //Field shot:[LShot;
   1235:	iload_1
   1236:	aaload
   1237:	invokevirtual	#195; //Method Shot.remove:()V
   1240:	aload_0
   1241:	getfield	#38; //Field ufo:[LUfo;
   1244:	iload_3
   1245:	aaload
   1246:	dup
   1247:	getfield	#221; //Field Ufo.hits:I
   1250:	iconst_1
   1251:	isub
   1252:	putfield	#221; //Field Ufo.hits:I
   1255:	aload_0
   1256:	aload_0
   1257:	getfield	#38; //Field ufo:[LUfo;
   1260:	iload_3
   1261:	aaload
   1262:	getfield	#222; //Field Ufo.x:F
   1265:	aload_0
   1266:	getfield	#38; //Field ufo:[LUfo;
   1269:	iload_3
   1270:	aaload
   1271:	getfield	#223; //Field Ufo.y:F
   1274:	aload_0
   1275:	getfield	#38; //Field ufo:[LUfo;
   1278:	iload_3
   1279:	aaload
   1280:	getfield	#224; //Field Ufo.speed:F
   1283:	aload_0
   1284:	getfield	#38; //Field ufo:[LUfo;
   1287:	iload_3
   1288:	aaload
   1289:	getfield	#225; //Field Ufo.dir:F
   1292:	aload_0
   1293:	getfield	#38; //Field ufo:[LUfo;
   1296:	iload_3
   1297:	aaload
   1298:	getfield	#226; //Field Ufo.angle:F
   1301:	aload_0
   1302:	getfield	#38; //Field ufo:[LUfo;
   1305:	iload_3
   1306:	aaload
   1307:	getfield	#227; //Field Ufo.hitmask:Lgame2d/Bitmap;
   1310:	invokevirtual	#228; //Method addHit:(FFFFFLgame2d/Bitmap;)V
   1313:	aload_0
   1314:	getfield	#128; //Field sound:Lgame2d/Sound;
   1317:	getstatic	#229; //Field Snd.hit:Lgame2d/Sample;
   1320:	iconst_0
   1321:	invokevirtual	#166; //Method game2d/Sound.play:(Lgame2d/Sample;Z)V
   1324:	aload_0
   1325:	getfield	#38; //Field ufo:[LUfo;
   1328:	iload_3
   1329:	aaload
   1330:	getfield	#221; //Field Ufo.hits:I
   1333:	ifge	1521
   1336:	aload_0
   1337:	getfield	#128; //Field sound:Lgame2d/Sound;
   1340:	getstatic	#230; //Field Snd.ufoexp:Lgame2d/Sample;
   1343:	iconst_1
   1344:	invokevirtual	#166; //Method game2d/Sound.play:(Lgame2d/Sample;Z)V
   1347:	aload_0
   1348:	aload_0
   1349:	getfield	#38; //Field ufo:[LUfo;
   1352:	iload_3
   1353:	aaload
   1354:	getfield	#222; //Field Ufo.x:F
   1357:	aload_0
   1358:	getfield	#38; //Field ufo:[LUfo;
   1361:	iload_3
   1362:	aaload
   1363:	getfield	#223; //Field Ufo.y:F
   1366:	aload_0
   1367:	getfield	#38; //Field ufo:[LUfo;
   1370:	iload_3
   1371:	aaload
   1372:	getfield	#224; //Field Ufo.speed:F
   1375:	aload_0
   1376:	getfield	#38; //Field ufo:[LUfo;
   1379:	iload_3
   1380:	aaload
   1381:	getfield	#225; //Field Ufo.dir:F
   1384:	aload_0
   1385:	getfield	#38; //Field ufo:[LUfo;
   1388:	iload_3
   1389:	aaload
   1390:	getfield	#226; //Field Ufo.angle:F
   1393:	invokevirtual	#201; //Method addExplosion:(FFFFF)V
   1396:	aload_0
   1397:	getfield	#38; //Field ufo:[LUfo;
   1400:	iload_3
   1401:	aaload
   1402:	getfield	#231; //Field Ufo.points:I
   1405:	invokestatic	#203; //Method Score.add:(I)V
   1408:	aload_0
   1409:	aload_0
   1410:	getfield	#38; //Field ufo:[LUfo;
   1413:	iload_3
   1414:	aaload
   1415:	getfield	#222; //Field Ufo.x:F
   1418:	aload_0
   1419:	getfield	#38; //Field ufo:[LUfo;
   1422:	iload_3
   1423:	aaload
   1424:	getfield	#223; //Field Ufo.y:F
   1427:	aload_0
   1428:	getfield	#38; //Field ufo:[LUfo;
   1431:	iload_3
   1432:	aaload
   1433:	getfield	#231; //Field Ufo.points:I
   1436:	invokevirtual	#204; //Method addPoint:(FFI)V
   1439:	aload_0
   1440:	getfield	#38; //Field ufo:[LUfo;
   1443:	iload_3
   1444:	aaload
   1445:	invokevirtual	#232; //Method Ufo.remove:()V
   1448:	invokestatic	#161; //Method game2d/Rnd.get:()I
   1451:	iconst_3
   1452:	iand
   1453:	iconst_3
   1454:	if_icmpeq	1464
   1457:	getstatic	#233; //Field Powers.level:I
   1460:	iconst_2
   1461:	if_icmpge	1521
   1464:	aload_0
   1465:	getfield	#43; //Field powerup:LPowerup;
   1468:	getfield	#234; //Field Powerup.status:Z
   1471:	ifne	1521
   1474:	aload_0
   1475:	getfield	#43; //Field powerup:LPowerup;
   1478:	aload_0
   1479:	getfield	#24; //Field ship:LShip;
   1482:	aload_0
   1483:	getfield	#38; //Field ufo:[LUfo;
   1486:	iload_3
   1487:	aaload
   1488:	getfield	#222; //Field Ufo.x:F
   1491:	aload_0
   1492:	getfield	#38; //Field ufo:[LUfo;
   1495:	iload_3
   1496:	aaload
   1497:	getfield	#223; //Field Ufo.y:F
   1500:	invokevirtual	#235; //Method Powerup.add:(LShip;FF)V
   1503:	aload_0
   1504:	getfield	#43; //Field powerup:LPowerup;
   1507:	invokevirtual	#236; //Method Powerup.setLevel:()V
   1510:	aload_0
   1511:	getfield	#58; //Field plist:Lgame2d/PropList;
   1514:	aload_0
   1515:	getfield	#43; //Field powerup:LPowerup;
   1518:	invokevirtual	#237; //Method game2d/PropList.add:(Lgame2d/Prop;)V
   1521:	aload_0
   1522:	getfield	#46; //Field extralife:LExtralife;
   1525:	getfield	#238; //Field Extralife.status:Z
   1528:	ifeq	1694
   1531:	aload_0
   1532:	getfield	#36; //Field shot:[LShot;
   1535:	iload_1
   1536:	aaload
   1537:	aload_0
   1538:	getfield	#46; //Field extralife:LExtralife;
   1541:	invokestatic	#187; //Method game2d/Collision.check:(Lgame2d/Prop;Lgame2d/Prop;)Z
   1544:	ifeq	1694
   1547:	aload_0
   1548:	getfield	#36; //Field shot:[LShot;
   1551:	iload_1
   1552:	aaload
   1553:	invokevirtual	#195; //Method Shot.remove:()V
   1556:	aload_0
   1557:	getfield	#46; //Field extralife:LExtralife;
   1560:	dup
   1561:	getfield	#239; //Field Extralife.hits:I
   1564:	iconst_1
   1565:	isub
   1566:	putfield	#239; //Field Extralife.hits:I
   1569:	aload_0
   1570:	aload_0
   1571:	getfield	#46; //Field extralife:LExtralife;
   1574:	getfield	#240; //Field Extralife.x:F
   1577:	aload_0
   1578:	getfield	#46; //Field extralife:LExtralife;
   1581:	getfield	#241; //Field Extralife.y:F
   1584:	aload_0
   1585:	getfield	#46; //Field extralife:LExtralife;
   1588:	getfield	#242; //Field Extralife.speed:F
   1591:	aload_0
   1592:	getfield	#46; //Field extralife:LExtralife;
   1595:	getfield	#243; //Field Extralife.dir:F
   1598:	aload_0
   1599:	getfield	#46; //Field extralife:LExtralife;
   1602:	getfield	#244; //Field Extralife.angle:F
   1605:	aload_0
   1606:	getfield	#46; //Field extralife:LExtralife;
   1609:	getfield	#245; //Field Extralife.hitmask:Lgame2d/Bitmap;
   1612:	invokevirtual	#228; //Method addHit:(FFFFFLgame2d/Bitmap;)V
   1615:	aload_0
   1616:	getfield	#128; //Field sound:Lgame2d/Sound;
   1619:	getstatic	#229; //Field Snd.hit:Lgame2d/Sample;
   1622:	iconst_0
   1623:	invokevirtual	#166; //Method game2d/Sound.play:(Lgame2d/Sample;Z)V
   1626:	aload_0
   1627:	getfield	#46; //Field extralife:LExtralife;
   1630:	getfield	#239; //Field Extralife.hits:I
   1633:	ifge	1694
   1636:	aload_0
   1637:	getfield	#128; //Field sound:Lgame2d/Sound;
   1640:	getstatic	#230; //Field Snd.ufoexp:Lgame2d/Sample;
   1643:	iconst_1
   1644:	invokevirtual	#166; //Method game2d/Sound.play:(Lgame2d/Sample;Z)V
   1647:	aload_0
   1648:	aload_0
   1649:	getfield	#46; //Field extralife:LExtralife;
   1652:	getfield	#240; //Field Extralife.x:F
   1655:	aload_0
   1656:	getfield	#46; //Field extralife:LExtralife;
   1659:	getfield	#241; //Field Extralife.y:F
   1662:	aload_0
   1663:	getfield	#46; //Field extralife:LExtralife;
   1666:	getfield	#242; //Field Extralife.speed:F
   1669:	aload_0
   1670:	getfield	#46; //Field extralife:LExtralife;
   1673:	getfield	#243; //Field Extralife.dir:F
   1676:	aload_0
   1677:	getfield	#46; //Field extralife:LExtralife;
   1680:	getfield	#244; //Field Extralife.angle:F
   1683:	invokevirtual	#201; //Method addExplosion:(FFFFF)V
   1686:	aload_0
   1687:	getfield	#46; //Field extralife:LExtralife;
   1690:	iconst_0
   1691:	putfield	#238; //Field Extralife.status:Z
   1694:	iinc	1, 1
   1697:	goto	645
   1700:	aload_0
   1701:	getfield	#43; //Field powerup:LPowerup;
   1704:	getfield	#234; //Field Powerup.status:Z
   1707:	ifeq	1873
   1710:	aload_0
   1711:	getfield	#24; //Field ship:LShip;
   1714:	aload_0
   1715:	getfield	#43; //Field powerup:LPowerup;
   1718:	invokestatic	#187; //Method game2d/Collision.check:(Lgame2d/Prop;Lgame2d/Prop;)Z
   1721:	ifeq	1873
   1724:	getstatic	#233; //Field Powers.level:I
   1727:	iconst_1
   1728:	iadd
   1729:	putstatic	#233; //Field Powers.level:I
   1732:	getstatic	#233; //Field Powers.level:I
   1735:	bipush	6
   1737:	if_icmple	1745
   1740:	bipush	6
   1742:	putstatic	#233; //Field Powers.level:I
   1745:	getstatic	#233; //Field Powers.level:I
   1748:	iconst_4
   1749:	if_icmpne	1756
   1752:	iconst_4
   1753:	putstatic	#246; //Field Powers.shield:I
   1756:	getstatic	#233; //Field Powers.level:I
   1759:	iconst_5
   1760:	if_icmpne	1767
   1763:	iconst_1
   1764:	putstatic	#247; //Field Powers.wingman:Z
   1767:	getstatic	#233; //Field Powers.level:I
   1770:	bipush	6
   1772:	if_icmpne	1805
   1775:	aload_0
   1776:	aload_0
   1777:	getfield	#43; //Field powerup:LPowerup;
   1780:	getfield	#248; //Field Powerup.x:F
   1783:	aload_0
   1784:	getfield	#43; //Field powerup:LPowerup;
   1787:	getfield	#249; //Field Powerup.y:F
   1790:	sipush	2500
   1793:	invokevirtual	#204; //Method addPoint:(FFI)V
   1796:	sipush	2500
   1799:	invokestatic	#203; //Method Score.add:(I)V
   1802:	goto	1840
   1805:	aload_0
   1806:	aload_0
   1807:	getfield	#43; //Field powerup:LPowerup;
   1810:	getfield	#248; //Field Powerup.x:F
   1813:	aload_0
   1814:	getfield	#43; //Field powerup:LPowerup;
   1817:	getfield	#249; //Field Powerup.y:F
   1820:	aload_0
   1821:	getfield	#43; //Field powerup:LPowerup;
   1824:	getfield	#250; //Field Powerup.points:I
   1827:	invokevirtual	#204; //Method addPoint:(FFI)V
   1830:	aload_0
   1831:	getfield	#43; //Field powerup:LPowerup;
   1834:	getfield	#250; //Field Powerup.points:I
   1837:	invokestatic	#203; //Method Score.add:(I)V
   1840:	invokestatic	#251; //Method Powers.updateLevel:()V
   1843:	aload_0
   1844:	getfield	#128; //Field sound:Lgame2d/Sound;
   1847:	getstatic	#252; //Field Snd.powerup1:Lgame2d/Sample;
   1850:	iconst_0
   1851:	invokevirtual	#166; //Method game2d/Sound.play:(Lgame2d/Sample;Z)V
   1854:	aload_0
   1855:	getfield	#128; //Field sound:Lgame2d/Sound;
   1858:	getstatic	#253; //Field Snd.powerup2:Lgame2d/Sample;
   1861:	iconst_0
   1862:	invokevirtual	#166; //Method game2d/Sound.play:(Lgame2d/Sample;Z)V
   1865:	aload_0
   1866:	getfield	#43; //Field powerup:LPowerup;
   1869:	iconst_0
   1870:	putfield	#234; //Field Powerup.status:Z
   1873:	getstatic	#254; //Field Score.current:I
   1876:	aload_0
   1877:	getfield	#255; //Field nextExtralifeScore:I
   1880:	if_icmplt	1916
   1883:	aload_0
   1884:	getfield	#46; //Field extralife:LExtralife;
   1887:	getfield	#238; //Field Extralife.status:Z
   1890:	ifne	1916
   1893:	aload_0
   1894:	getfield	#46; //Field extralife:LExtralife;
   1897:	aload_0
   1898:	getfield	#24; //Field ship:LShip;
   1901:	invokevirtual	#256; //Method Extralife.add:(LShip;)V
   1904:	aload_0
   1905:	dup
   1906:	getfield	#255; //Field nextExtralifeScore:I
   1909:	sipush	10000
   1912:	iadd
   1913:	putfield	#255; //Field nextExtralifeScore:I
   1916:	aload_0
   1917:	getfield	#46; //Field extralife:LExtralife;
   1920:	getfield	#238; //Field Extralife.status:Z
   1923:	ifeq	1995
   1926:	aload_0
   1927:	getfield	#24; //Field ship:LShip;
   1930:	aload_0
   1931:	getfield	#46; //Field extralife:LExtralife;
   1934:	invokestatic	#187; //Method game2d/Collision.check:(Lgame2d/Prop;Lgame2d/Prop;)Z
   1937:	ifeq	1995
   1940:	aload_0
   1941:	getfield	#128; //Field sound:Lgame2d/Sound;
   1944:	getstatic	#252; //Field Snd.powerup1:Lgame2d/Sample;
   1947:	iconst_0
   1948:	invokevirtual	#166; //Method game2d/Sound.play:(Lgame2d/Sample;Z)V
   1951:	aload_0
   1952:	getfield	#128; //Field sound:Lgame2d/Sound;
   1955:	getstatic	#253; //Field Snd.powerup2:Lgame2d/Sample;
   1958:	iconst_0
   1959:	invokevirtual	#166; //Method game2d/Sound.play:(Lgame2d/Sample;Z)V
   1962:	aload_0
   1963:	dup
   1964:	getfield	#257; //Field lives:I
   1967:	iconst_1
   1968:	iadd
   1969:	putfield	#257; //Field lives:I
   1972:	aload_0
   1973:	getfield	#257; //Field lives:I
   1976:	bipush	99
   1978:	if_icmple	1987
   1981:	aload_0
   1982:	bipush	99
   1984:	putfield	#257; //Field lives:I
   1987:	aload_0
   1988:	getfield	#46; //Field extralife:LExtralife;
   1991:	iconst_0
   1992:	putfield	#238; //Field Extralife.status:Z
   1995:	iconst_0
   1996:	istore_1
   1997:	iload_1
   1998:	aload_0
   1999:	getfield	#14; //Field MAX_EXPS:I
   2002:	if_icmpge	2020
   2005:	aload_0
   2006:	getfield	#26; //Field exp:[LExp;
   2009:	iload_1
   2010:	aaload
   2011:	invokevirtual	#258; //Method Exp.update:()V
   2014:	iinc	1, 1
   2017:	goto	1997
   2020:	iconst_0
   2021:	istore_1
   2022:	iload_1
   2023:	aload_0
   2024:	getfield	#15; //Field MAX_HITS:I
   2027:	if_icmpge	2045
   2030:	aload_0
   2031:	getfield	#28; //Field hit:[LHit;
   2034:	iload_1
   2035:	aaload
   2036:	invokevirtual	#259; //Method Hit.update:()V
   2039:	iinc	1, 1
   2042:	goto	2022
   2045:	iconst_0
   2046:	istore_1
   2047:	iload_1
   2048:	aload_0
   2049:	getfield	#16; //Field MAX_POINTS:I
   2052:	if_icmpge	2070
   2055:	aload_0
   2056:	getfield	#30; //Field point:[LPoints;
   2059:	iload_1
   2060:	aaload
   2061:	invokevirtual	#260; //Method Points.update:()V
   2064:	iinc	1, 1
   2067:	goto	2047
   2070:	iconst_0
   2071:	istore_1
   2072:	iload_1
   2073:	getstatic	#185; //Field Level.rocks:I
   2076:	if_icmpge	2094
   2079:	aload_0
   2080:	getfield	#32; //Field rock:[LRock;
   2083:	iload_1
   2084:	aaload
   2085:	invokevirtual	#261; //Method Rock.update:()V
   2088:	iinc	1, 1
   2091:	goto	2072
   2094:	iconst_0
   2095:	istore_1
   2096:	iload_1
   2097:	getstatic	#191; //Field Level.meteors:I
   2100:	if_icmpge	2118
   2103:	aload_0
   2104:	getfield	#34; //Field meteor:[LMeteor;
   2107:	iload_1
   2108:	aaload
   2109:	invokevirtual	#262; //Method Meteor.update:()V
   2112:	iinc	1, 1
   2115:	goto	2096
   2118:	iconst_0
   2119:	istore_1
   2120:	iload_1
   2121:	getstatic	#162; //Field Level.ufos:I
   2124:	if_icmpge	2146
   2127:	aload_0
   2128:	getfield	#38; //Field ufo:[LUfo;
   2131:	iload_1
   2132:	aaload
   2133:	aload_0
   2134:	getfield	#24; //Field ship:LShip;
   2137:	invokevirtual	#263; //Method Ufo.update:(LShip;)V
   2140:	iinc	1, 1
   2143:	goto	2120
   2146:	iconst_0
   2147:	istore_1
   2148:	iload_1
   2149:	getstatic	#167; //Field Level.ufoshots:I
   2152:	if_icmpge	2170
   2155:	aload_0
   2156:	getfield	#40; //Field ufoshot:[LUfoshot;
   2159:	iload_1
   2160:	aaload
   2161:	invokevirtual	#264; //Method Ufoshot.update:()V
   2164:	iinc	1, 1
   2167:	goto	2148
   2170:	aload_0
   2171:	getfield	#43; //Field powerup:LPowerup;
   2174:	invokevirtual	#265; //Method Powerup.update:()V
   2177:	aload_0
   2178:	getfield	#46; //Field extralife:LExtralife;
   2181:	invokevirtual	#266; //Method Extralife.update:()V
   2184:	aload_0
   2185:	dup
   2186:	getfield	#181; //Field shot_timer:I
   2189:	iconst_1
   2190:	iadd
   2191:	putfield	#181; //Field shot_timer:I
   2194:	iconst_0
   2195:	istore_1
   2196:	iload_1
   2197:	getstatic	#267; //Field game2d/AnimList.count:I
   2200:	if_icmpge	2217
   2203:	getstatic	#268; //Field game2d/AnimList.anim:[Lgame2d/Anim;
   2206:	iload_1
   2207:	aaload
   2208:	invokevirtual	#269; //Method game2d/Anim.update:()V
   2211:	iinc	1, 1
   2214:	goto	2196
   2217:	iconst_0
   2218:	ireturn

public void gameFrame();
  Code:
   0:	iconst_0
   1:	istore_2
   2:	iconst_0
   3:	istore_1
   4:	iload_1
   5:	aload_0
   6:	getfield	#55; //Field MAX_LIGHTS:I
   9:	if_icmpge	112
   12:	aload_0
   13:	getfield	#58; //Field plist:Lgame2d/PropList;
   16:	getfield	#270; //Field game2d/PropList.prop:[Lgame2d/Prop;
   19:	iload_1
   20:	aaload
   21:	getfield	#271; //Field game2d/Prop.status:Z
   24:	ifeq	106
   27:	aload_0
   28:	getfield	#60; //Field light:[Lgame2d/Light;
   31:	iload_2
   32:	aaload
   33:	aload_0
   34:	getfield	#58; //Field plist:Lgame2d/PropList;
   37:	getfield	#270; //Field game2d/PropList.prop:[Lgame2d/Prop;
   40:	iload_1
   41:	aaload
   42:	getfield	#272; //Field game2d/Prop.x:F
   45:	f2i
   46:	putfield	#273; //Field game2d/Light.x:I
   49:	aload_0
   50:	getfield	#60; //Field light:[Lgame2d/Light;
   53:	iload_2
   54:	aaload
   55:	aload_0
   56:	getfield	#58; //Field plist:Lgame2d/PropList;
   59:	getfield	#270; //Field game2d/PropList.prop:[Lgame2d/Prop;
   62:	iload_1
   63:	aaload
   64:	getfield	#274; //Field game2d/Prop.y:F
   67:	f2i
   68:	putfield	#275; //Field game2d/Light.y:I
   71:	aload_0
   72:	getfield	#60; //Field light:[Lgame2d/Light;
   75:	iload_2
   76:	aaload
   77:	aload_0
   78:	getfield	#58; //Field plist:Lgame2d/PropList;
   81:	getfield	#270; //Field game2d/PropList.prop:[Lgame2d/Prop;
   84:	iload_1
   85:	aaload
   86:	getfield	#276; //Field game2d/Prop.light_color:I
   89:	putfield	#277; //Field game2d/Light.color:I
   92:	iinc	2, 1
   95:	iload_2
   96:	aload_0
   97:	getfield	#55; //Field MAX_LIGHTS:I
   100:	if_icmplt	106
   103:	goto	112
   106:	iinc	1, 1
   109:	goto	4
   112:	aload_0
   113:	getfield	#83; //Field backbuf:Lgame2d/Bitmap;
   116:	invokestatic	#278; //Method Stars.render:(Lgame2d/Bitmap;)V
   119:	iconst_0
   120:	istore_1
   121:	iload_1
   122:	getstatic	#185; //Field Level.rocks:I
   125:	if_icmpge	209
   128:	aload_0
   129:	getfield	#32; //Field rock:[LRock;
   132:	iload_1
   133:	aaload
   134:	getfield	#279; //Field Rock.status:Z
   137:	ifeq	203
   140:	aload_0
   141:	getfield	#32; //Field rock:[LRock;
   144:	iload_1
   145:	aaload
   146:	getfield	#208; //Field Rock.anim:Lgame2d/Anim;
   149:	invokevirtual	#49; //Method game2d/Anim.frame:()Lgame2d/Bitmap;
   152:	aload_0
   153:	getfield	#83; //Field backbuf:Lgame2d/Bitmap;
   156:	aload_0
   157:	getfield	#32; //Field rock:[LRock;
   160:	iload_1
   161:	aaload
   162:	getfield	#196; //Field Rock.x:F
   165:	f2i
   166:	aload_0
   167:	getfield	#32; //Field rock:[LRock;
   170:	iload_1
   171:	aaload
   172:	getfield	#197; //Field Rock.y:F
   175:	f2i
   176:	aload_0
   177:	getfield	#32; //Field rock:[LRock;
   180:	iload_1
   181:	aaload
   182:	getfield	#200; //Field Rock.angle:F
   185:	f2i
   186:	aload_0
   187:	getfield	#32; //Field rock:[LRock;
   190:	iload_1
   191:	aaload
   192:	getfield	#280; //Field Rock.scale:F
   195:	aload_0
   196:	getfield	#60; //Field light:[Lgame2d/Light;
   199:	iload_2
   200:	invokevirtual	#281; //Method game2d/Bitmap.rotateLitSprite:(Lgame2d/Bitmap;IIIF[Lgame2d/Light;I)V
   203:	iinc	1, 1
   206:	goto	121
   209:	iconst_0
   210:	istore_1
   211:	iload_1
   212:	getstatic	#191; //Field Level.meteors:I
   215:	if_icmpge	299
   218:	aload_0
   219:	getfield	#34; //Field meteor:[LMeteor;
   222:	iload_1
   223:	aaload
   224:	getfield	#282; //Field Meteor.status:Z
   227:	ifeq	293
   230:	aload_0
   231:	getfield	#34; //Field meteor:[LMeteor;
   234:	iload_1
   235:	aaload
   236:	getfield	#283; //Field Meteor.anim:Lgame2d/Anim;
   239:	invokevirtual	#49; //Method game2d/Anim.frame:()Lgame2d/Bitmap;
   242:	aload_0
   243:	getfield	#83; //Field backbuf:Lgame2d/Bitmap;
   246:	aload_0
   247:	getfield	#34; //Field meteor:[LMeteor;
   250:	iload_1
   251:	aaload
   252:	getfield	#214; //Field Meteor.x:F
   255:	f2i
   256:	aload_0
   257:	getfield	#34; //Field meteor:[LMeteor;
   260:	iload_1
   261:	aaload
   262:	getfield	#215; //Field Meteor.y:F
   265:	f2i
   266:	aload_0
   267:	getfield	#34; //Field meteor:[LMeteor;
   270:	iload_1
   271:	aaload
   272:	getfield	#218; //Field Meteor.angle:F
   275:	f2i
   276:	aload_0
   277:	getfield	#34; //Field meteor:[LMeteor;
   280:	iload_1
   281:	aaload
   282:	getfield	#284; //Field Meteor.scale:F
   285:	aload_0
   286:	getfield	#60; //Field light:[Lgame2d/Light;
   289:	iload_2
   290:	invokevirtual	#281; //Method game2d/Bitmap.rotateLitSprite:(Lgame2d/Bitmap;IIIF[Lgame2d/Light;I)V
   293:	iinc	1, 1
   296:	goto	211
   299:	iconst_0
   300:	istore_1
   301:	iload_1
   302:	getstatic	#167; //Field Level.ufoshots:I
   305:	if_icmpge	384
   308:	aload_0
   309:	getfield	#40; //Field ufoshot:[LUfoshot;
   312:	iload_1
   313:	aaload
   314:	getfield	#168; //Field Ufoshot.status:Z
   317:	ifeq	378
   320:	aload_0
   321:	getfield	#40; //Field ufoshot:[LUfoshot;
   324:	iload_1
   325:	aaload
   326:	getfield	#285; //Field Ufoshot.anim:Lgame2d/Anim;
   329:	invokevirtual	#49; //Method game2d/Anim.frame:()Lgame2d/Bitmap;
   332:	aload_0
   333:	getfield	#83; //Field backbuf:Lgame2d/Bitmap;
   336:	aload_0
   337:	getfield	#40; //Field ufoshot:[LUfoshot;
   340:	iload_1
   341:	aaload
   342:	getfield	#286; //Field Ufoshot.x:F
   345:	f2i
   346:	aload_0
   347:	getfield	#40; //Field ufoshot:[LUfoshot;
   350:	iload_1
   351:	aaload
   352:	getfield	#287; //Field Ufoshot.y:F
   355:	f2i
   356:	aload_0
   357:	getfield	#40; //Field ufoshot:[LUfoshot;
   360:	iload_1
   361:	aaload
   362:	getfield	#288; //Field Ufoshot.angle:F
   365:	f2i
   366:	aload_0
   367:	getfield	#40; //Field ufoshot:[LUfoshot;
   370:	iload_1
   371:	aaload
   372:	getfield	#289; //Field Ufoshot.scale:F
   375:	invokevirtual	#290; //Method game2d/Bitmap.rotateSprite:(Lgame2d/Bitmap;IIIF)V
   378:	iinc	1, 1
   381:	goto	301
   384:	iconst_0
   385:	istore_1
   386:	iload_1
   387:	getstatic	#192; //Field Level.shots:I
   390:	if_icmpge	469
   393:	aload_0
   394:	getfield	#36; //Field shot:[LShot;
   397:	iload_1
   398:	aaload
   399:	getfield	#194; //Field Shot.status:Z
   402:	ifeq	463
   405:	aload_0
   406:	getfield	#36; //Field shot:[LShot;
   409:	iload_1
   410:	aaload
   411:	getfield	#291; //Field Shot.anim:Lgame2d/Anim;
   414:	invokevirtual	#49; //Method game2d/Anim.frame:()Lgame2d/Bitmap;
   417:	aload_0
   418:	getfield	#83; //Field backbuf:Lgame2d/Bitmap;
   421:	aload_0
   422:	getfield	#36; //Field shot:[LShot;
   425:	iload_1
   426:	aaload
   427:	getfield	#292; //Field Shot.x:F
   430:	f2i
   431:	aload_0
   432:	getfield	#36; //Field shot:[LShot;
   435:	iload_1
   436:	aaload
   437:	getfield	#293; //Field Shot.y:F
   440:	f2i
   441:	aload_0
   442:	getfield	#36; //Field shot:[LShot;
   445:	iload_1
   446:	aaload
   447:	getfield	#294; //Field Shot.angle:F
   450:	f2i
   451:	aload_0
   452:	getfield	#36; //Field shot:[LShot;
   455:	iload_1
   456:	aaload
   457:	getfield	#295; //Field Shot.scale:F
   460:	invokevirtual	#290; //Method game2d/Bitmap.rotateSprite:(Lgame2d/Bitmap;IIIF)V
   463:	iinc	1, 1
   466:	goto	386
   469:	iconst_0
   470:	istore_1
   471:	iload_1
   472:	getstatic	#162; //Field Level.ufos:I
   475:	if_icmpge	559
   478:	aload_0
   479:	getfield	#38; //Field ufo:[LUfo;
   482:	iload_1
   483:	aaload
   484:	getfield	#163; //Field Ufo.status:Z
   487:	ifeq	553
   490:	aload_0
   491:	getfield	#38; //Field ufo:[LUfo;
   494:	iload_1
   495:	aaload
   496:	getfield	#296; //Field Ufo.anim:Lgame2d/Anim;
   499:	invokevirtual	#49; //Method game2d/Anim.frame:()Lgame2d/Bitmap;
   502:	aload_0
   503:	getfield	#83; //Field backbuf:Lgame2d/Bitmap;
   506:	aload_0
   507:	getfield	#38; //Field ufo:[LUfo;
   510:	iload_1
   511:	aaload
   512:	getfield	#222; //Field Ufo.x:F
   515:	f2i
   516:	aload_0
   517:	getfield	#38; //Field ufo:[LUfo;
   520:	iload_1
   521:	aaload
   522:	getfield	#223; //Field Ufo.y:F
   525:	f2i
   526:	aload_0
   527:	getfield	#38; //Field ufo:[LUfo;
   530:	iload_1
   531:	aaload
   532:	getfield	#226; //Field Ufo.angle:F
   535:	f2i
   536:	aload_0
   537:	getfield	#38; //Field ufo:[LUfo;
   540:	iload_1
   541:	aaload
   542:	getfield	#297; //Field Ufo.scale:F
   545:	aload_0
   546:	getfield	#60; //Field light:[Lgame2d/Light;
   549:	iload_2
   550:	invokevirtual	#281; //Method game2d/Bitmap.rotateLitSprite:(Lgame2d/Bitmap;IIIF[Lgame2d/Light;I)V
   553:	iinc	1, 1
   556:	goto	471
   559:	iconst_0
   560:	istore_1
   561:	iload_1
   562:	aload_0
   563:	getfield	#14; //Field MAX_EXPS:I
   566:	if_icmpge	645
   569:	aload_0
   570:	getfield	#26; //Field exp:[LExp;
   573:	iload_1
   574:	aaload
   575:	getfield	#298; //Field Exp.status:Z
   578:	ifeq	639
   581:	aload_0
   582:	getfield	#26; //Field exp:[LExp;
   585:	iload_1
   586:	aaload
   587:	getfield	#299; //Field Exp.anim:Lgame2d/Anim;
   590:	invokevirtual	#49; //Method game2d/Anim.frame:()Lgame2d/Bitmap;
   593:	aload_0
   594:	getfield	#83; //Field backbuf:Lgame2d/Bitmap;
   597:	aload_0
   598:	getfield	#26; //Field exp:[LExp;
   601:	iload_1
   602:	aaload
   603:	getfield	#300; //Field Exp.x:F
   606:	f2i
   607:	aload_0
   608:	getfield	#26; //Field exp:[LExp;
   611:	iload_1
   612:	aaload
   613:	getfield	#301; //Field Exp.y:F
   616:	f2i
   617:	aload_0
   618:	getfield	#26; //Field exp:[LExp;
   621:	iload_1
   622:	aaload
   623:	getfield	#302; //Field Exp.angle:F
   626:	f2i
   627:	aload_0
   628:	getfield	#26; //Field exp:[LExp;
   631:	iload_1
   632:	aaload
   633:	getfield	#303; //Field Exp.scale:F
   636:	invokevirtual	#290; //Method game2d/Bitmap.rotateSprite:(Lgame2d/Bitmap;IIIF)V
   639:	iinc	1, 1
   642:	goto	561
   645:	aload_0
   646:	getfield	#43; //Field powerup:LPowerup;
   649:	getfield	#234; //Field Powerup.status:Z
   652:	ifeq	703
   655:	aload_0
   656:	getfield	#43; //Field powerup:LPowerup;
   659:	getfield	#304; //Field Powerup.anim:Lgame2d/Anim;
   662:	invokevirtual	#49; //Method game2d/Anim.frame:()Lgame2d/Bitmap;
   665:	aload_0
   666:	getfield	#83; //Field backbuf:Lgame2d/Bitmap;
   669:	aload_0
   670:	getfield	#43; //Field powerup:LPowerup;
   673:	getfield	#248; //Field Powerup.x:F
   676:	f2i
   677:	aload_0
   678:	getfield	#43; //Field powerup:LPowerup;
   681:	getfield	#249; //Field Powerup.y:F
   684:	f2i
   685:	aload_0
   686:	getfield	#43; //Field powerup:LPowerup;
   689:	getfield	#305; //Field Powerup.angle:F
   692:	f2i
   693:	aload_0
   694:	getfield	#43; //Field powerup:LPowerup;
   697:	getfield	#306; //Field Powerup.scale:F
   700:	invokevirtual	#290; //Method game2d/Bitmap.rotateSprite:(Lgame2d/Bitmap;IIIF)V
   703:	aload_0
   704:	getfield	#46; //Field extralife:LExtralife;
   707:	getfield	#238; //Field Extralife.status:Z
   710:	ifeq	872
   713:	aload_0
   714:	getfield	#46; //Field extralife:LExtralife;
   717:	getfield	#307; //Field Extralife.anim:Lgame2d/Anim;
   720:	invokevirtual	#49; //Method game2d/Anim.frame:()Lgame2d/Bitmap;
   723:	aload_0
   724:	getfield	#83; //Field backbuf:Lgame2d/Bitmap;
   727:	aload_0
   728:	getfield	#46; //Field extralife:LExtralife;
   731:	getfield	#240; //Field Extralife.x:F
   734:	f2i
   735:	aload_0
   736:	getfield	#46; //Field extralife:LExtralife;
   739:	getfield	#241; //Field Extralife.y:F
   742:	f2i
   743:	aload_0
   744:	getfield	#46; //Field extralife:LExtralife;
   747:	getfield	#244; //Field Extralife.angle:F
   750:	f2i
   751:	aload_0
   752:	getfield	#46; //Field extralife:LExtralife;
   755:	getfield	#308; //Field Extralife.scale:F
   758:	invokevirtual	#290; //Method game2d/Bitmap.rotateSprite:(Lgame2d/Bitmap;IIIF)V
   761:	aload_0
   762:	getfield	#46; //Field extralife:LExtralife;
   765:	getfield	#238; //Field Extralife.status:Z
   768:	ifeq	815
   771:	getstatic	#309; //Field Sprite.thrust1:Lgame2d/Anim;
   774:	invokevirtual	#49; //Method game2d/Anim.frame:()Lgame2d/Bitmap;
   777:	aload_0
   778:	getfield	#83; //Field backbuf:Lgame2d/Bitmap;
   781:	aload_0
   782:	getfield	#46; //Field extralife:LExtralife;
   785:	getfield	#240; //Field Extralife.x:F
   788:	f2i
   789:	aload_0
   790:	getfield	#46; //Field extralife:LExtralife;
   793:	getfield	#241; //Field Extralife.y:F
   796:	f2i
   797:	aload_0
   798:	getfield	#46; //Field extralife:LExtralife;
   801:	getfield	#244; //Field Extralife.angle:F
   804:	f2i
   805:	aload_0
   806:	getfield	#46; //Field extralife:LExtralife;
   809:	getfield	#308; //Field Extralife.scale:F
   812:	invokevirtual	#290; //Method game2d/Bitmap.rotateSprite:(Lgame2d/Bitmap;IIIF)V
   815:	ldc_w	#310; //float 0.5f
   818:	ldc	#135; //float 0.1f
   820:	getstatic	#311; //Field game2d/Trig.sin:[F
   823:	aload_0
   824:	getfield	#134; //Field pulse:I
   827:	sipush	1023
   830:	iand
   831:	faload
   832:	fmul
   833:	invokestatic	#312; //Method java/lang/Math.abs:(F)F
   836:	fadd
   837:	fstore_3
   838:	aload_0
   839:	getfield	#51; //Field font16x32:Lgame2d/FontBmp;
   842:	aload_0
   843:	getfield	#83; //Field backbuf:Lgame2d/Bitmap;
   846:	aload_0
   847:	getfield	#46; //Field extralife:LExtralife;
   850:	getfield	#240; //Field Extralife.x:F
   853:	f2i
   854:	aload_0
   855:	getfield	#46; //Field extralife:LExtralife;
   858:	getfield	#241; //Field Extralife.y:F
   861:	f2i
   862:	bipush	24
   864:	iadd
   865:	ldc_w	#313; //String Rescue
   868:	fload_3
   869:	invokevirtual	#314; //Method game2d/FontBmp.drawCenteredString:(Lgame2d/Bitmap;IILjava/lang/String;F)V
   872:	getstatic	#177; //Field Powers.thrust:Z
   875:	ifeq	928
   878:	getstatic	#180; //Field Powers.thrustActive:Z
   881:	ifeq	928
   884:	getstatic	#309; //Field Sprite.thrust1:Lgame2d/Anim;
   887:	invokevirtual	#49; //Method game2d/Anim.frame:()Lgame2d/Bitmap;
   890:	aload_0
   891:	getfield	#83; //Field backbuf:Lgame2d/Bitmap;
   894:	aload_0
   895:	getfield	#24; //Field ship:LShip;
   898:	getfield	#172; //Field Ship.x:F
   901:	f2i
   902:	aload_0
   903:	getfield	#24; //Field ship:LShip;
   906:	getfield	#170; //Field Ship.y:F
   909:	f2i
   910:	aload_0
   911:	getfield	#24; //Field ship:LShip;
   914:	getfield	#175; //Field Ship.angle:F
   917:	f2i
   918:	aload_0
   919:	getfield	#24; //Field ship:LShip;
   922:	getfield	#315; //Field Ship.scale:F
   925:	invokevirtual	#290; //Method game2d/Bitmap.rotateSprite:(Lgame2d/Bitmap;IIIF)V
   928:	aload_0
   929:	getfield	#24; //Field ship:LShip;
   932:	getfield	#316; //Field Ship.status:Z
   935:	ifeq	991
   938:	aload_0
   939:	getfield	#24; //Field ship:LShip;
   942:	getfield	#317; //Field Ship.anim:Lgame2d/Anim;
   945:	invokevirtual	#49; //Method game2d/Anim.frame:()Lgame2d/Bitmap;
   948:	aload_0
   949:	getfield	#83; //Field backbuf:Lgame2d/Bitmap;
   952:	aload_0
   953:	getfield	#24; //Field ship:LShip;
   956:	getfield	#172; //Field Ship.x:F
   959:	f2i
   960:	aload_0
   961:	getfield	#24; //Field ship:LShip;
   964:	getfield	#170; //Field Ship.y:F
   967:	f2i
   968:	aload_0
   969:	getfield	#24; //Field ship:LShip;
   972:	getfield	#175; //Field Ship.angle:F
   975:	f2i
   976:	aload_0
   977:	getfield	#24; //Field ship:LShip;
   980:	getfield	#315; //Field Ship.scale:F
   983:	aload_0
   984:	getfield	#60; //Field light:[Lgame2d/Light;
   987:	iload_2
   988:	invokevirtual	#281; //Method game2d/Bitmap.rotateLitSprite:(Lgame2d/Bitmap;IIIF[Lgame2d/Light;I)V
   991:	getstatic	#246; //Field Powers.shield:I
   994:	iconst_1
   995:	if_icmple	1042
   998:	getstatic	#318; //Field Sprite.shield1:Lgame2d/Anim;
   1001:	invokevirtual	#49; //Method game2d/Anim.frame:()Lgame2d/Bitmap;
   1004:	aload_0
   1005:	getfield	#83; //Field backbuf:Lgame2d/Bitmap;
   1008:	aload_0
   1009:	getfield	#24; //Field ship:LShip;
   1012:	getfield	#172; //Field Ship.x:F
   1015:	f2i
   1016:	aload_0
   1017:	getfield	#24; //Field ship:LShip;
   1020:	getfield	#170; //Field Ship.y:F
   1023:	f2i
   1024:	aload_0
   1025:	getfield	#24; //Field ship:LShip;
   1028:	getfield	#175; //Field Ship.angle:F
   1031:	f2i
   1032:	aload_0
   1033:	getfield	#24; //Field ship:LShip;
   1036:	getfield	#315; //Field Ship.scale:F
   1039:	invokevirtual	#290; //Method game2d/Bitmap.rotateSprite:(Lgame2d/Bitmap;IIIF)V
   1042:	getstatic	#247; //Field Powers.wingman:Z
   1045:	ifeq	1097
   1048:	getstatic	#319; //Field Sprite.wingman1:Lgame2d/Anim;
   1051:	invokevirtual	#49; //Method game2d/Anim.frame:()Lgame2d/Bitmap;
   1054:	aload_0
   1055:	getfield	#83; //Field backbuf:Lgame2d/Bitmap;
   1058:	aload_0
   1059:	getfield	#24; //Field ship:LShip;
   1062:	getfield	#172; //Field Ship.x:F
   1065:	f2i
   1066:	aload_0
   1067:	getfield	#24; //Field ship:LShip;
   1070:	getfield	#170; //Field Ship.y:F
   1073:	f2i
   1074:	aload_0
   1075:	getfield	#24; //Field ship:LShip;
   1078:	getfield	#175; //Field Ship.angle:F
   1081:	f2i
   1082:	aload_0
   1083:	getfield	#24; //Field ship:LShip;
   1086:	getfield	#315; //Field Ship.scale:F
   1089:	aload_0
   1090:	getfield	#60; //Field light:[Lgame2d/Light;
   1093:	iload_2
   1094:	invokevirtual	#281; //Method game2d/Bitmap.rotateLitSprite:(Lgame2d/Bitmap;IIIF[Lgame2d/Light;I)V
   1097:	iconst_0
   1098:	istore_1
   1099:	iload_1
   1100:	aload_0
   1101:	getfield	#15; //Field MAX_HITS:I
   1104:	if_icmpge	1180
   1107:	aload_0
   1108:	getfield	#28; //Field hit:[LHit;
   1111:	iload_1
   1112:	aaload
   1113:	getfield	#320; //Field Hit.status:Z
   1116:	ifeq	1174
   1119:	aload_0
   1120:	getfield	#28; //Field hit:[LHit;
   1123:	iload_1
   1124:	aaload
   1125:	getfield	#321; //Field Hit.hitmask:Lgame2d/Bitmap;
   1128:	aload_0
   1129:	getfield	#83; //Field backbuf:Lgame2d/Bitmap;
   1132:	aload_0
   1133:	getfield	#28; //Field hit:[LHit;
   1136:	iload_1
   1137:	aaload
   1138:	getfield	#322; //Field Hit.x:F
   1141:	f2i
   1142:	aload_0
   1143:	getfield	#28; //Field hit:[LHit;
   1146:	iload_1
   1147:	aaload
   1148:	getfield	#323; //Field Hit.y:F
   1151:	f2i
   1152:	aload_0
   1153:	getfield	#28; //Field hit:[LHit;
   1156:	iload_1
   1157:	aaload
   1158:	getfield	#324; //Field Hit.angle:F
   1161:	f2i
   1162:	aload_0
   1163:	getfield	#28; //Field hit:[LHit;
   1166:	iload_1
   1167:	aaload
   1168:	getfield	#325; //Field Hit.scale:F
   1171:	invokevirtual	#290; //Method game2d/Bitmap.rotateSprite:(Lgame2d/Bitmap;IIIF)V
   1174:	iinc	1, 1
   1177:	goto	1099
   1180:	iconst_0
   1181:	istore_1
   1182:	iload_1
   1183:	aload_0
   1184:	getfield	#16; //Field MAX_POINTS:I
   1187:	if_icmpge	1260
   1190:	aload_0
   1191:	getfield	#30; //Field point:[LPoints;
   1194:	iload_1
   1195:	aaload
   1196:	getfield	#326; //Field Points.status:Z
   1199:	ifeq	1254
   1202:	aload_0
   1203:	getfield	#51; //Field font16x32:Lgame2d/FontBmp;
   1206:	aload_0
   1207:	getfield	#83; //Field backbuf:Lgame2d/Bitmap;
   1210:	aload_0
   1211:	getfield	#30; //Field point:[LPoints;
   1214:	iload_1
   1215:	aaload
   1216:	getfield	#327; //Field Points.x:F
   1219:	f2i
   1220:	aload_0
   1221:	getfield	#30; //Field point:[LPoints;
   1224:	iload_1
   1225:	aaload
   1226:	getfield	#328; //Field Points.y:F
   1229:	f2i
   1230:	aload_0
   1231:	getfield	#30; //Field point:[LPoints;
   1234:	iload_1
   1235:	aaload
   1236:	getfield	#329; //Field Points.value:I
   1239:	invokestatic	#330; //Method java/lang/String.valueOf:(I)Ljava/lang/String;
   1242:	aload_0
   1243:	getfield	#30; //Field point:[LPoints;
   1246:	iload_1
   1247:	aaload
   1248:	getfield	#331; //Field Points.scale:F
   1251:	invokevirtual	#332; //Method game2d/FontBmp.drawString:(Lgame2d/Bitmap;IILjava/lang/String;F)V
   1254:	iinc	1, 1
   1257:	goto	1182
   1260:	aload_0
   1261:	getfield	#51; //Field font16x32:Lgame2d/FontBmp;
   1264:	aload_0
   1265:	getfield	#83; //Field backbuf:Lgame2d/Bitmap;
   1268:	iconst_0
   1269:	iconst_0
   1270:	getstatic	#254; //Field Score.current:I
   1273:	invokestatic	#330; //Method java/lang/String.valueOf:(I)Ljava/lang/String;
   1276:	fconst_1
   1277:	invokevirtual	#332; //Method game2d/FontBmp.drawString:(Lgame2d/Bitmap;IILjava/lang/String;F)V
   1280:	getstatic	#81; //Field game2d/Screen.w:I
   1283:	bipush	16
   1285:	isub
   1286:	istore_3
   1287:	iconst_0
   1288:	istore_1
   1289:	iload_1
   1290:	aload_0
   1291:	getfield	#257; //Field lives:I
   1294:	if_icmpge	1340
   1297:	iload_1
   1298:	iconst_4
   1299:	if_icmple	1305
   1302:	goto	1340
   1305:	aload_0
   1306:	getfield	#24; //Field ship:LShip;
   1309:	getfield	#317; //Field Ship.anim:Lgame2d/Anim;
   1312:	invokevirtual	#49; //Method game2d/Anim.frame:()Lgame2d/Bitmap;
   1315:	aload_0
   1316:	getfield	#83; //Field backbuf:Lgame2d/Bitmap;
   1319:	iload_3
   1320:	bipush	16
   1322:	sipush	256
   1325:	ldc_w	#310; //float 0.5f
   1328:	invokevirtual	#290; //Method game2d/Bitmap.rotateSprite:(Lgame2d/Bitmap;IIIF)V
   1331:	iinc	3, -32
   1334:	iinc	1, 1
   1337:	goto	1289
   1340:	aload_0
   1341:	getfield	#257; //Field lives:I
   1344:	iconst_5
   1345:	if_icmple	1374
   1348:	aload_0
   1349:	getfield	#51; //Field font16x32:Lgame2d/FontBmp;
   1352:	aload_0
   1353:	getfield	#83; //Field backbuf:Lgame2d/Bitmap;
   1356:	iload_3
   1357:	bipush	16
   1359:	isub
   1360:	iconst_4
   1361:	aload_0
   1362:	getfield	#257; //Field lives:I
   1365:	invokestatic	#330; //Method java/lang/String.valueOf:(I)Ljava/lang/String;
   1368:	ldc_w	#333; //float 0.75f
   1371:	invokevirtual	#332; //Method game2d/FontBmp.drawString:(Lgame2d/Bitmap;IILjava/lang/String;F)V
   1374:	getstatic	#334; //Field Sprite.cross1:Lgame2d/Anim;
   1377:	invokevirtual	#49; //Method game2d/Anim.frame:()Lgame2d/Bitmap;
   1380:	aload_0
   1381:	getfield	#83; //Field backbuf:Lgame2d/Bitmap;
   1384:	aload_0
   1385:	getfield	#122; //Field input:Lgame2d/Input;
   1388:	getfield	#173; //Field game2d/Input.mousex:I
   1391:	aload_0
   1392:	getfield	#122; //Field input:Lgame2d/Input;
   1395:	getfield	#171; //Field game2d/Input.mousey:I
   1398:	sipush	256
   1401:	fconst_1
   1402:	invokevirtual	#290; //Method game2d/Bitmap.rotateSprite:(Lgame2d/Bitmap;IIIF)V
   1405:	aload_0
   1406:	getfield	#6; //Field paused:Z
   1409:	ifeq	1448
   1412:	aload_0
   1413:	getfield	#83; //Field backbuf:Lgame2d/Bitmap;
   1416:	iconst_0
   1417:	iconst_0
   1418:	aload_0
   1419:	getfield	#83; //Field backbuf:Lgame2d/Bitmap;
   1422:	getfield	#86; //Field game2d/Bitmap.w:I
   1425:	iconst_1
   1426:	isub
   1427:	aload_0
   1428:	getfield	#83; //Field backbuf:Lgame2d/Bitmap;
   1431:	getfield	#87; //Field game2d/Bitmap.h:I
   1434:	iconst_1
   1435:	isub
   1436:	iconst_0
   1437:	iconst_0
   1438:	iconst_0
   1439:	invokestatic	#335; //Method game2d/Col.makeRGB:(III)I
   1442:	sipush	160
   1445:	invokevirtual	#336; //Method game2d/Bitmap.rectfill:(IIIIII)V
   1448:	return

public boolean menuLoop();
  Code:
   0:	aload_0
   1:	getfield	#128; //Field sound:Lgame2d/Sound;
   4:	getstatic	#337; //Field Snd.music1:Lgame2d/Sample;
   7:	iconst_0
   8:	invokevirtual	#166; //Method game2d/Sound.play:(Lgame2d/Sample;Z)V
   11:	aload_0
   12:	getfield	#128; //Field sound:Lgame2d/Sound;
   15:	getstatic	#338; //Field Snd.music2:Lgame2d/Sample;
   18:	iconst_0
   19:	invokevirtual	#166; //Method game2d/Sound.play:(Lgame2d/Sample;Z)V
   22:	aload_0
   23:	getfield	#128; //Field sound:Lgame2d/Sound;
   26:	getstatic	#339; //Field Snd.music3:Lgame2d/Sample;
   29:	iconst_0
   30:	invokevirtual	#166; //Method game2d/Sound.play:(Lgame2d/Sample;Z)V
   33:	invokestatic	#158; //Method Stars.update:()V
   36:	aload_0
   37:	invokevirtual	#340; //Method updateScroll:()V
   40:	aload_0
   41:	getfield	#122; //Field input:Lgame2d/Input;
   44:	getfield	#176; //Field game2d/Input.button1:Z
   47:	ifne	55
   50:	aload_0
   51:	iconst_1
   52:	putfield	#4; //Field go_ahead:Z
   55:	aload_0
   56:	getfield	#4; //Field go_ahead:Z
   59:	ifeq	81
   62:	aload_0
   63:	getfield	#122; //Field input:Lgame2d/Input;
   66:	getfield	#176; //Field game2d/Input.button1:Z
   69:	ifeq	81
   72:	aload_0
   73:	getfield	#128; //Field sound:Lgame2d/Sound;
   76:	invokevirtual	#160; //Method game2d/Sound.quiet:()V
   79:	iconst_1
   80:	ireturn
   81:	iconst_0
   82:	ireturn

public void menuFrame();
  Code:
   0:	aload_0
   1:	getfield	#54; //Field tile:Lgame2d/Bitmap;
   4:	invokestatic	#278; //Method Stars.render:(Lgame2d/Bitmap;)V
   7:	aload_0
   8:	getfield	#54; //Field tile:Lgame2d/Bitmap;
   11:	aload_0
   12:	getfield	#83; //Field backbuf:Lgame2d/Bitmap;
   15:	getstatic	#81; //Field game2d/Screen.w:I
   18:	iconst_2
   19:	idiv
   20:	getstatic	#82; //Field game2d/Screen.h:I
   23:	iconst_2
   24:	idiv
   25:	aload_0
   26:	getfield	#8; //Field menu_stars_angle:F
   29:	f2i
   30:	aload_0
   31:	getfield	#9; //Field menu_stars_scale:F
   34:	invokevirtual	#341; //Method game2d/Bitmap.rotozoom:(Lgame2d/Bitmap;IIIF)V
   37:	getstatic	#342; //Field Sprite.coolguy6:Lgame2d/Anim;
   40:	invokevirtual	#49; //Method game2d/Anim.frame:()Lgame2d/Bitmap;
   43:	aload_0
   44:	getfield	#83; //Field backbuf:Lgame2d/Bitmap;
   47:	iconst_0
   48:	iconst_0
   49:	getstatic	#81; //Field game2d/Screen.w:I
   52:	getstatic	#342; //Field Sprite.coolguy6:Lgame2d/Anim;
   55:	getfield	#343; //Field game2d/Anim.w:I
   58:	isub
   59:	iconst_2
   60:	idiv
   61:	getstatic	#82; //Field game2d/Screen.h:I
   64:	getstatic	#342; //Field Sprite.coolguy6:Lgame2d/Anim;
   67:	getfield	#344; //Field game2d/Anim.h:I
   70:	isub
   71:	iconst_2
   72:	idiv
   73:	bipush	32
   75:	isub
   76:	getstatic	#342; //Field Sprite.coolguy6:Lgame2d/Anim;
   79:	getfield	#343; //Field game2d/Anim.w:I
   82:	getstatic	#342; //Field Sprite.coolguy6:Lgame2d/Anim;
   85:	getfield	#344; //Field game2d/Anim.h:I
   88:	invokevirtual	#345; //Method game2d/Bitmap.blit:(Lgame2d/Bitmap;IIIIII)V
   91:	aload_0
   92:	getfield	#51; //Field font16x32:Lgame2d/FontBmp;
   95:	aload_0
   96:	getfield	#83; //Field backbuf:Lgame2d/Bitmap;
   99:	getstatic	#81; //Field game2d/Screen.w:I
   102:	iconst_2
   103:	idiv
   104:	bipush	16
   106:	getstatic	#139; //Field Score.high:I
   109:	invokestatic	#330; //Method java/lang/String.valueOf:(I)Ljava/lang/String;
   112:	fconst_1
   113:	invokevirtual	#314; //Method game2d/FontBmp.drawCenteredString:(Lgame2d/Bitmap;IILjava/lang/String;F)V
   116:	fconst_1
   117:	ldc2_w	#346; //double 0.25d
   120:	getstatic	#311; //Field game2d/Trig.sin:[F
   123:	aload_0
   124:	getfield	#134; //Field pulse:I
   127:	sipush	1023
   130:	iand
   131:	faload
   132:	f2d
   133:	dmul
   134:	invokestatic	#348; //Method java/lang/Math.abs:(D)D
   137:	d2f
   138:	fadd
   139:	fstore_1
   140:	aload_0
   141:	getfield	#51; //Field font16x32:Lgame2d/FontBmp;
   144:	aload_0
   145:	getfield	#83; //Field backbuf:Lgame2d/Bitmap;
   148:	getstatic	#81; //Field game2d/Screen.w:I
   151:	iconst_2
   152:	idiv
   153:	getstatic	#82; //Field game2d/Screen.h:I
   156:	iconst_2
   157:	idiv
   158:	bipush	64
   160:	iadd
   161:	ldc_w	#349; //String Click to Play!
   164:	fload_1
   165:	invokevirtual	#314; //Method game2d/FontBmp.drawCenteredString:(Lgame2d/Bitmap;IILjava/lang/String;F)V
   168:	aload_0
   169:	getfield	#51; //Field font16x32:Lgame2d/FontBmp;
   172:	aload_0
   173:	getfield	#83; //Field backbuf:Lgame2d/Bitmap;
   176:	getstatic	#81; //Field game2d/Screen.w:I
   179:	iconst_2
   180:	idiv
   181:	getstatic	#82; //Field game2d/Screen.h:I
   184:	bipush	8
   186:	isub
   187:	ldc_w	#350; //String Copyright (c) 2012 Joe Davisson. All Rights Reserved.
   190:	ldc_w	#310; //float 0.5f
   193:	invokevirtual	#314; //Method game2d/FontBmp.drawCenteredString:(Lgame2d/Bitmap;IILjava/lang/String;F)V
   196:	new	#71; //class java/lang/String
   199:	dup
   200:	aload_0
   201:	getfield	#77; //Field scrolltemp:[C
   204:	invokespecial	#351; //Method java/lang/String."<init>":([C)V
   207:	astore_2
   208:	aload_0
   209:	getfield	#51; //Field font16x32:Lgame2d/FontBmp;
   212:	aload_0
   213:	getfield	#83; //Field backbuf:Lgame2d/Bitmap;
   216:	iconst_0
   217:	aload_0
   218:	getfield	#75; //Field scrolltick:I
   221:	isub
   222:	sipush	400
   225:	aload_2
   226:	fconst_1
   227:	invokevirtual	#332; //Method game2d/FontBmp.drawString:(Lgame2d/Bitmap;IILjava/lang/String;F)V
   230:	return

public boolean levelLoop();
  Code:
   0:	invokestatic	#158; //Method Stars.update:()V
   3:	aload_0
   4:	dup
   5:	getfield	#11; //Field menu_delay:I
   8:	iconst_1
   9:	iadd
   10:	putfield	#11; //Field menu_delay:I
   13:	aload_0
   14:	getfield	#11; //Field menu_delay:I
   17:	bipush	125
   19:	if_icmpge	24
   22:	iconst_0
   23:	ireturn
   24:	aload_0
   25:	iconst_0
   26:	putfield	#11; //Field menu_delay:I
   29:	iconst_1
   30:	ireturn

public void levelFrame();
  Code:
   0:	aload_0
   1:	getfield	#54; //Field tile:Lgame2d/Bitmap;
   4:	invokestatic	#278; //Method Stars.render:(Lgame2d/Bitmap;)V
   7:	aload_0
   8:	getfield	#54; //Field tile:Lgame2d/Bitmap;
   11:	aload_0
   12:	getfield	#83; //Field backbuf:Lgame2d/Bitmap;
   15:	getstatic	#81; //Field game2d/Screen.w:I
   18:	iconst_2
   19:	idiv
   20:	getstatic	#82; //Field game2d/Screen.h:I
   23:	iconst_2
   24:	idiv
   25:	aload_0
   26:	getfield	#8; //Field menu_stars_angle:F
   29:	f2i
   30:	aload_0
   31:	getfield	#9; //Field menu_stars_scale:F
   34:	invokevirtual	#341; //Method game2d/Bitmap.rotozoom:(Lgame2d/Bitmap;IIIF)V
   37:	fconst_2
   38:	ldc_w	#310; //float 0.5f
   41:	getstatic	#311; //Field game2d/Trig.sin:[F
   44:	aload_0
   45:	getfield	#134; //Field pulse:I
   48:	sipush	1023
   51:	iand
   52:	faload
   53:	fmul
   54:	invokestatic	#312; //Method java/lang/Math.abs:(F)F
   57:	fadd
   58:	fstore_1
   59:	aload_0
   60:	getfield	#51; //Field font16x32:Lgame2d/FontBmp;
   63:	aload_0
   64:	getfield	#83; //Field backbuf:Lgame2d/Bitmap;
   67:	getstatic	#81; //Field game2d/Screen.w:I
   70:	iconst_2
   71:	idiv
   72:	getstatic	#82; //Field game2d/Screen.h:I
   75:	iconst_2
   76:	idiv
   77:	bipush	64
   79:	isub
   80:	new	#352; //class java/lang/StringBuilder
   83:	dup
   84:	invokespecial	#353; //Method java/lang/StringBuilder."<init>":()V
   87:	ldc_w	#354; //String Level 
   90:	invokevirtual	#355; //Method java/lang/StringBuilder.append:(Ljava/lang/String;)Ljava/lang/StringBuilder;
   93:	getstatic	#356; //Field Level.current:I
   96:	iconst_1
   97:	iadd
   98:	invokestatic	#330; //Method java/lang/String.valueOf:(I)Ljava/lang/String;
   101:	invokevirtual	#355; //Method java/lang/StringBuilder.append:(Ljava/lang/String;)Ljava/lang/StringBuilder;
   104:	invokevirtual	#357; //Method java/lang/StringBuilder.toString:()Ljava/lang/String;
   107:	fload_1
   108:	invokevirtual	#314; //Method game2d/FontBmp.drawCenteredString:(Lgame2d/Bitmap;IILjava/lang/String;F)V
   111:	aload_0
   112:	getfield	#257; //Field lives:I
   115:	istore_3
   116:	iload_3
   117:	iconst_5
   118:	if_icmple	123
   121:	iconst_5
   122:	istore_3
   123:	bipush	64
   125:	istore	4
   127:	iload	4
   129:	iload_3
   130:	iconst_1
   131:	isub
   132:	iflt	141
   135:	iload_3
   136:	iconst_1
   137:	isub
   138:	goto	142
   141:	iconst_0
   142:	imul
   143:	istore	5
   145:	getstatic	#81; //Field game2d/Screen.w:I
   148:	iconst_2
   149:	idiv
   150:	iload	5
   152:	iconst_2
   153:	idiv
   154:	isub
   155:	istore	6
   157:	iconst_0
   158:	istore_2
   159:	iload_2
   160:	iload_3
   161:	if_icmpge	208
   164:	aload_0
   165:	getfield	#24; //Field ship:LShip;
   168:	getfield	#317; //Field Ship.anim:Lgame2d/Anim;
   171:	invokevirtual	#49; //Method game2d/Anim.frame:()Lgame2d/Bitmap;
   174:	aload_0
   175:	getfield	#83; //Field backbuf:Lgame2d/Bitmap;
   178:	iload	6
   180:	getstatic	#82; //Field game2d/Screen.h:I
   183:	iconst_2
   184:	idiv
   185:	bipush	64
   187:	iadd
   188:	sipush	256
   191:	fconst_1
   192:	invokevirtual	#290; //Method game2d/Bitmap.rotateSprite:(Lgame2d/Bitmap;IIIF)V
   195:	iload	6
   197:	iload	4
   199:	iadd
   200:	istore	6
   202:	iinc	2, 1
   205:	goto	159
   208:	aload_0
   209:	getfield	#257; //Field lives:I
   212:	iconst_1
   213:	if_icmple	271
   216:	aload_0
   217:	getfield	#51; //Field font16x32:Lgame2d/FontBmp;
   220:	aload_0
   221:	getfield	#83; //Field backbuf:Lgame2d/Bitmap;
   224:	getstatic	#81; //Field game2d/Screen.w:I
   227:	iconst_2
   228:	idiv
   229:	getstatic	#82; //Field game2d/Screen.h:I
   232:	iconst_2
   233:	idiv
   234:	sipush	128
   237:	iadd
   238:	new	#352; //class java/lang/StringBuilder
   241:	dup
   242:	invokespecial	#353; //Method java/lang/StringBuilder."<init>":()V
   245:	aload_0
   246:	getfield	#257; //Field lives:I
   249:	invokestatic	#330; //Method java/lang/String.valueOf:(I)Ljava/lang/String;
   252:	invokevirtual	#355; //Method java/lang/StringBuilder.append:(Ljava/lang/String;)Ljava/lang/StringBuilder;
   255:	ldc_w	#358; //String  Ships Remaining
   258:	invokevirtual	#355; //Method java/lang/StringBuilder.append:(Ljava/lang/String;)Ljava/lang/StringBuilder;
   261:	invokevirtual	#357; //Method java/lang/StringBuilder.toString:()Ljava/lang/String;
   264:	fconst_1
   265:	invokevirtual	#314; //Method game2d/FontBmp.drawCenteredString:(Lgame2d/Bitmap;IILjava/lang/String;F)V
   268:	goto	361
   271:	aload_0
   272:	getfield	#257; //Field lives:I
   275:	ifle	333
   278:	aload_0
   279:	getfield	#51; //Field font16x32:Lgame2d/FontBmp;
   282:	aload_0
   283:	getfield	#83; //Field backbuf:Lgame2d/Bitmap;
   286:	getstatic	#81; //Field game2d/Screen.w:I
   289:	iconst_2
   290:	idiv
   291:	getstatic	#82; //Field game2d/Screen.h:I
   294:	iconst_2
   295:	idiv
   296:	sipush	128
   299:	iadd
   300:	new	#352; //class java/lang/StringBuilder
   303:	dup
   304:	invokespecial	#353; //Method java/lang/StringBuilder."<init>":()V
   307:	aload_0
   308:	getfield	#257; //Field lives:I
   311:	invokestatic	#330; //Method java/lang/String.valueOf:(I)Ljava/lang/String;
   314:	invokevirtual	#355; //Method java/lang/StringBuilder.append:(Ljava/lang/String;)Ljava/lang/StringBuilder;
   317:	ldc_w	#359; //String  Ship Remaining
   320:	invokevirtual	#355; //Method java/lang/StringBuilder.append:(Ljava/lang/String;)Ljava/lang/StringBuilder;
   323:	invokevirtual	#357; //Method java/lang/StringBuilder.toString:()Ljava/lang/String;
   326:	fconst_1
   327:	invokevirtual	#314; //Method game2d/FontBmp.drawCenteredString:(Lgame2d/Bitmap;IILjava/lang/String;F)V
   330:	goto	361
   333:	aload_0
   334:	getfield	#51; //Field font16x32:Lgame2d/FontBmp;
   337:	aload_0
   338:	getfield	#83; //Field backbuf:Lgame2d/Bitmap;
   341:	getstatic	#81; //Field game2d/Screen.w:I
   344:	iconst_2
   345:	idiv
   346:	getstatic	#82; //Field game2d/Screen.h:I
   349:	iconst_2
   350:	idiv
   351:	bipush	96
   353:	iadd
   354:	ldc_w	#360; //String Last Chance!
   357:	fconst_1
   358:	invokevirtual	#314; //Method game2d/FontBmp.drawCenteredString:(Lgame2d/Bitmap;IILjava/lang/String;F)V
   361:	return

public boolean gameOverLoop();
  Code:
   0:	invokestatic	#158; //Method Stars.update:()V
   3:	aload_0
   4:	dup
   5:	getfield	#11; //Field menu_delay:I
   8:	iconst_1
   9:	iadd
   10:	putfield	#11; //Field menu_delay:I
   13:	aload_0
   14:	getfield	#11; //Field menu_delay:I
   17:	sipush	250
   20:	if_icmpge	25
   23:	iconst_0
   24:	ireturn
   25:	aload_0
   26:	iconst_0
   27:	putfield	#11; //Field menu_delay:I
   30:	iconst_1
   31:	ireturn

public void gameOverFrame();
  Code:
   0:	aload_0
   1:	getfield	#54; //Field tile:Lgame2d/Bitmap;
   4:	invokestatic	#278; //Method Stars.render:(Lgame2d/Bitmap;)V
   7:	aload_0
   8:	getfield	#54; //Field tile:Lgame2d/Bitmap;
   11:	aload_0
   12:	getfield	#83; //Field backbuf:Lgame2d/Bitmap;
   15:	getstatic	#81; //Field game2d/Screen.w:I
   18:	iconst_2
   19:	idiv
   20:	getstatic	#82; //Field game2d/Screen.h:I
   23:	iconst_2
   24:	idiv
   25:	aload_0
   26:	getfield	#8; //Field menu_stars_angle:F
   29:	f2i
   30:	aload_0
   31:	getfield	#9; //Field menu_stars_scale:F
   34:	invokevirtual	#341; //Method game2d/Bitmap.rotozoom:(Lgame2d/Bitmap;IIIF)V
   37:	fconst_2
   38:	ldc_w	#310; //float 0.5f
   41:	getstatic	#311; //Field game2d/Trig.sin:[F
   44:	aload_0
   45:	getfield	#134; //Field pulse:I
   48:	sipush	1023
   51:	iand
   52:	faload
   53:	fmul
   54:	invokestatic	#312; //Method java/lang/Math.abs:(F)F
   57:	fadd
   58:	fstore_1
   59:	aload_0
   60:	getfield	#51; //Field font16x32:Lgame2d/FontBmp;
   63:	aload_0
   64:	getfield	#83; //Field backbuf:Lgame2d/Bitmap;
   67:	getstatic	#81; //Field game2d/Screen.w:I
   70:	iconst_2
   71:	idiv
   72:	getstatic	#82; //Field game2d/Screen.h:I
   75:	iconst_2
   76:	idiv
   77:	ldc_w	#361; //String Game Over
   80:	fload_1
   81:	invokevirtual	#314; //Method game2d/FontBmp.drawCenteredString:(Lgame2d/Bitmap;IILjava/lang/String;F)V
   84:	fconst_1
   85:	ldc2_w	#346; //double 0.25d
   88:	getstatic	#311; //Field game2d/Trig.sin:[F
   91:	aload_0
   92:	getfield	#134; //Field pulse:I
   95:	sipush	1023
   98:	iand
   99:	faload
   100:	f2d
   101:	dmul
   102:	invokestatic	#348; //Method java/lang/Math.abs:(D)D
   105:	d2f
   106:	fadd
   107:	fstore_1
   108:	aload_0
   109:	getfield	#51; //Field font16x32:Lgame2d/FontBmp;
   112:	aload_0
   113:	getfield	#83; //Field backbuf:Lgame2d/Bitmap;
   116:	getstatic	#81; //Field game2d/Screen.w:I
   119:	iconst_2
   120:	idiv
   121:	getstatic	#82; //Field game2d/Screen.h:I
   124:	iconst_2
   125:	idiv
   126:	bipush	64
   128:	iadd
   129:	new	#352; //class java/lang/StringBuilder
   132:	dup
   133:	invokespecial	#353; //Method java/lang/StringBuilder."<init>":()V
   136:	ldc_w	#362; //String You got to Level 
   139:	invokevirtual	#355; //Method java/lang/StringBuilder.append:(Ljava/lang/String;)Ljava/lang/StringBuilder;
   142:	getstatic	#356; //Field Level.current:I
   145:	iconst_1
   146:	iadd
   147:	invokestatic	#330; //Method java/lang/String.valueOf:(I)Ljava/lang/String;
   150:	invokevirtual	#355; //Method java/lang/StringBuilder.append:(Ljava/lang/String;)Ljava/lang/StringBuilder;
   153:	ldc_w	#363; //String !
   156:	invokevirtual	#355; //Method java/lang/StringBuilder.append:(Ljava/lang/String;)Ljava/lang/StringBuilder;
   159:	invokevirtual	#357; //Method java/lang/StringBuilder.toString:()Ljava/lang/String;
   162:	fload_1
   163:	invokevirtual	#314; //Method game2d/FontBmp.drawCenteredString:(Lgame2d/Bitmap;IILjava/lang/String;F)V
   166:	return

public void loseLife(game2d.Prop);
  Code:
   0:	aload_0
   1:	aload_1
   2:	getfield	#272; //Field game2d/Prop.x:F
   5:	aload_1
   6:	getfield	#274; //Field game2d/Prop.y:F
   9:	aload_1
   10:	getfield	#364; //Field game2d/Prop.speed:F
   13:	aload_1
   14:	getfield	#365; //Field game2d/Prop.dir:F
   17:	aload_1
   18:	getfield	#366; //Field game2d/Prop.angle:F
   21:	invokevirtual	#201; //Method addExplosion:(FFFFF)V
   24:	aload_0
   25:	getfield	#128; //Field sound:Lgame2d/Sound;
   28:	getstatic	#367; //Field Snd.shipexp:Lgame2d/Sample;
   31:	iconst_0
   32:	invokevirtual	#166; //Method game2d/Sound.play:(Lgame2d/Sample;Z)V
   35:	aload_1
   36:	invokevirtual	#368; //Method game2d/Prop.remove:()V
   39:	getstatic	#246; //Field Powers.shield:I
   42:	iconst_1
   43:	isub
   44:	putstatic	#246; //Field Powers.shield:I
   47:	getstatic	#246; //Field Powers.shield:I
   50:	ifle	100
   53:	aload_0
   54:	aload_0
   55:	getfield	#24; //Field ship:LShip;
   58:	getfield	#172; //Field Ship.x:F
   61:	aload_0
   62:	getfield	#24; //Field ship:LShip;
   65:	getfield	#170; //Field Ship.y:F
   68:	aload_0
   69:	getfield	#24; //Field ship:LShip;
   72:	getfield	#369; //Field Ship.speed:F
   75:	aload_0
   76:	getfield	#24; //Field ship:LShip;
   79:	getfield	#370; //Field Ship.dir:F
   82:	aload_0
   83:	getfield	#24; //Field ship:LShip;
   86:	getfield	#175; //Field Ship.angle:F
   89:	aload_0
   90:	getfield	#24; //Field ship:LShip;
   93:	getfield	#371; //Field Ship.hitmask:Lgame2d/Bitmap;
   96:	invokevirtual	#228; //Method addHit:(FFFFFLgame2d/Bitmap;)V
   99:	return
   100:	aload_0
   101:	dup
   102:	getfield	#257; //Field lives:I
   105:	iconst_1
   106:	isub
   107:	putfield	#257; //Field lives:I
   110:	aload_0
   111:	getfield	#257; //Field lives:I
   114:	ifge	145
   117:	aload_0
   118:	iconst_3
   119:	putfield	#7; //Field game_mode:I
   122:	aload_0
   123:	getfield	#128; //Field sound:Lgame2d/Sound;
   126:	getstatic	#372; //Field Snd.gameover1:Lgame2d/Sample;
   129:	iconst_0
   130:	invokevirtual	#166; //Method game2d/Sound.play:(Lgame2d/Sample;Z)V
   133:	aload_0
   134:	getfield	#128; //Field sound:Lgame2d/Sound;
   137:	getstatic	#373; //Field Snd.gameover2:Lgame2d/Sample;
   140:	iconst_0
   141:	invokevirtual	#166; //Method game2d/Sound.play:(Lgame2d/Sample;Z)V
   144:	return
   145:	aload_0
   146:	aload_0
   147:	getfield	#24; //Field ship:LShip;
   150:	getfield	#172; //Field Ship.x:F
   153:	aload_0
   154:	getfield	#24; //Field ship:LShip;
   157:	getfield	#170; //Field Ship.y:F
   160:	aload_0
   161:	getfield	#24; //Field ship:LShip;
   164:	getfield	#369; //Field Ship.speed:F
   167:	aload_0
   168:	getfield	#24; //Field ship:LShip;
   171:	getfield	#370; //Field Ship.dir:F
   174:	aload_0
   175:	getfield	#24; //Field ship:LShip;
   178:	getfield	#175; //Field Ship.angle:F
   181:	invokevirtual	#201; //Method addExplosion:(FFFFF)V
   184:	aload_0
   185:	getfield	#128; //Field sound:Lgame2d/Sound;
   188:	getstatic	#367; //Field Snd.shipexp:Lgame2d/Sample;
   191:	iconst_0
   192:	invokevirtual	#166; //Method game2d/Sound.play:(Lgame2d/Sample;Z)V
   195:	invokestatic	#374; //Method Powers.removeLevel:()V
   198:	aload_0
   199:	iconst_1
   200:	putfield	#7; //Field game_mode:I
   203:	aload_0
   204:	invokespecial	#375; //Method restartLevel:()V
   207:	return

public void resetScroll();
  Code:
   0:	aload_0
   1:	getfield	#74; //Field scroller:Ljava/lang/String;
   4:	invokevirtual	#376; //Method java/lang/String.length:()I
   7:	istore_3
   8:	iconst_0
   9:	istore	4
   11:	aload_0
   12:	iconst_0
   13:	putfield	#75; //Field scrolltick:I
   16:	aload_0
   17:	iconst_0
   18:	putfield	#76; //Field scrollpos:I
   21:	aload_0
   22:	getfield	#76; //Field scrollpos:I
   25:	istore_1
   26:	iload_1
   27:	aload_0
   28:	getfield	#76; //Field scrollpos:I
   31:	bipush	41
   33:	iadd
   34:	if_icmpge	72
   37:	iload_1
   38:	istore_2
   39:	iload_2
   40:	iload_3
   41:	if_icmplt	48
   44:	iload_2
   45:	iload_3
   46:	isub
   47:	istore_2
   48:	aload_0
   49:	getfield	#77; //Field scrolltemp:[C
   52:	iload	4
   54:	iinc	4, 1
   57:	aload_0
   58:	getfield	#74; //Field scroller:Ljava/lang/String;
   61:	iload_2
   62:	invokevirtual	#377; //Method java/lang/String.charAt:(I)C
   65:	castore
   66:	iinc	1, 1
   69:	goto	26
   72:	return

public void updateScroll();
  Code:
   0:	aload_0
   1:	getfield	#74; //Field scroller:Ljava/lang/String;
   4:	invokevirtual	#376; //Method java/lang/String.length:()I
   7:	istore_3
   8:	iconst_0
   9:	istore	4
   11:	aload_0
   12:	dup
   13:	getfield	#75; //Field scrolltick:I
   16:	iconst_1
   17:	iadd
   18:	putfield	#75; //Field scrolltick:I
   21:	aload_0
   22:	getfield	#75; //Field scrolltick:I
   25:	bipush	15
   27:	if_icmple	109
   30:	aload_0
   31:	iconst_0
   32:	putfield	#75; //Field scrolltick:I
   35:	aload_0
   36:	getfield	#76; //Field scrollpos:I
   39:	istore_1
   40:	iload_1
   41:	aload_0
   42:	getfield	#76; //Field scrollpos:I
   45:	bipush	41
   47:	iadd
   48:	if_icmpge	86
   51:	iload_1
   52:	istore_2
   53:	iload_2
   54:	iload_3
   55:	if_icmplt	62
   58:	iload_2
   59:	iload_3
   60:	isub
   61:	istore_2
   62:	aload_0
   63:	getfield	#77; //Field scrolltemp:[C
   66:	iload	4
   68:	iinc	4, 1
   71:	aload_0
   72:	getfield	#74; //Field scroller:Ljava/lang/String;
   75:	iload_2
   76:	invokevirtual	#377; //Method java/lang/String.charAt:(I)C
   79:	castore
   80:	iinc	1, 1
   83:	goto	40
   86:	aload_0
   87:	dup
   88:	getfield	#76; //Field scrollpos:I
   91:	iconst_1
   92:	iadd
   93:	putfield	#76; //Field scrollpos:I
   96:	aload_0
   97:	getfield	#76; //Field scrollpos:I
   100:	iload_3
   101:	if_icmplt	109
   104:	aload_0
   105:	iconst_0
   106:	putfield	#76; //Field scrollpos:I
   109:	return

public void addExplosion(float, float, float, float, float);
  Code:
   0:	iconst_0
   1:	istore	6
   3:	iload	6
   5:	aload_0
   6:	getfield	#14; //Field MAX_EXPS:I
   9:	if_icmpge	34
   12:	aload_0
   13:	getfield	#26; //Field exp:[LExp;
   16:	iload	6
   18:	aaload
   19:	getfield	#298; //Field Exp.status:Z
   22:	ifne	28
   25:	goto	34
   28:	iinc	6, 1
   31:	goto	3
   34:	iload	6
   36:	aload_0
   37:	getfield	#14; //Field MAX_EXPS:I
   40:	if_icmpge	74
   43:	aload_0
   44:	getfield	#26; //Field exp:[LExp;
   47:	iload	6
   49:	aaload
   50:	fload_1
   51:	fload_2
   52:	fload_3
   53:	fload	4
   55:	fload	5
   57:	invokevirtual	#378; //Method Exp.add:(FFFFF)V
   60:	aload_0
   61:	getfield	#58; //Field plist:Lgame2d/PropList;
   64:	aload_0
   65:	getfield	#26; //Field exp:[LExp;
   68:	iload	6
   70:	aaload
   71:	invokevirtual	#237; //Method game2d/PropList.add:(Lgame2d/Prop;)V
   74:	return

public void addHit(float, float, float, float, float, game2d.Bitmap);
  Code:
   0:	iconst_0
   1:	istore	7
   3:	iload	7
   5:	aload_0
   6:	getfield	#15; //Field MAX_HITS:I
   9:	if_icmpge	34
   12:	aload_0
   13:	getfield	#28; //Field hit:[LHit;
   16:	iload	7
   18:	aaload
   19:	getfield	#320; //Field Hit.status:Z
   22:	ifne	28
   25:	goto	34
   28:	iinc	7, 1
   31:	goto	3
   34:	iload	7
   36:	aload_0
   37:	getfield	#15; //Field MAX_HITS:I
   40:	if_icmpge	62
   43:	aload_0
   44:	getfield	#28; //Field hit:[LHit;
   47:	iload	7
   49:	aaload
   50:	fload_1
   51:	fload_2
   52:	fload_3
   53:	fload	4
   55:	fload	5
   57:	aload	6
   59:	invokevirtual	#379; //Method Hit.add:(FFFFFLgame2d/Bitmap;)V
   62:	return

public void addPoint(float, float, int);
  Code:
   0:	iconst_0
   1:	istore	4
   3:	iload	4
   5:	aload_0
   6:	getfield	#16; //Field MAX_POINTS:I
   9:	if_icmpge	34
   12:	aload_0
   13:	getfield	#30; //Field point:[LPoints;
   16:	iload	4
   18:	aaload
   19:	getfield	#326; //Field Points.status:Z
   22:	ifne	28
   25:	goto	34
   28:	iinc	4, 1
   31:	goto	3
   34:	iload	4
   36:	aload_0
   37:	getfield	#16; //Field MAX_POINTS:I
   40:	if_icmpge	56
   43:	aload_0
   44:	getfield	#30; //Field point:[LPoints;
   47:	iload	4
   49:	aaload
   50:	fload_1
   51:	fload_2
   52:	iload_3
   53:	invokevirtual	#380; //Method Points.add:(FFI)V
   56:	return

public void paint(java.awt.Graphics);
  Code:
   0:	aload_0
   1:	getfield	#13; //Field paintok:Z
   4:	ifeq	34
   7:	aload_1
   8:	aload_0
   9:	getfield	#96; //Field bi:Ljava/awt/image/BufferedImage;
   12:	getstatic	#108; //Field game2d/Screen.xpos:I
   15:	getstatic	#109; //Field game2d/Screen.ypos:I
   18:	getstatic	#106; //Field game2d/Screen.scaledw:I
   21:	getstatic	#107; //Field game2d/Screen.scaledh:I
   24:	aconst_null
   25:	invokevirtual	#398; //Method java/awt/Graphics.drawImage:(Ljava/awt/Image;IIIILjava/awt/image/ImageObserver;)Z
   28:	pop
   29:	aload_0
   30:	iconst_0
   31:	putfield	#13; //Field paintok:Z
   34:	return

public void update(java.awt.Graphics);
  Code:
   0:	aload_0
   1:	getfield	#13; //Field paintok:Z
   4:	ifeq	12
   7:	aload_0
   8:	aload_1
   9:	invokevirtual	#399; //Method paint:(Ljava/awt/Graphics;)V
   12:	return

public void stop();
  Code:
   0:	return

public void destroy();
  Code:
   0:	return

}

